{"id": "52940", "author": "الحكم بن أبي الصلت", "abyat": [{"bayt": " لم يدعني الشوق إلا اقتادني طربا ولم يدع لي في غير الصبا أربا", "sadr": " لم يدعني الشوق إلا اقتادني طربا", "ajez": " ولم يدع لي في غير الصبا أربا"}, {"bayt": " وذو العلاقة من لج الغرام به وكلما ليم أو سيم النزوع أبي", "sadr": " وذو العلاقة من لج الغرام به", "ajez": " وكلما ليم أو سيم النزوع أبي"}, {"bayt": " كانت لنا وقفة بالشعب واحدة عنها تفرع هذا الحب وانشغبا", "sadr": " كانت لنا وقفة بالشعب واحدة", "ajez": " عنها تفرع هذا الحب وانشغبا"}, {"bayt": " ولائم لي لم أحفل ملامته ولا سمحت له مني بما طالبا", "sadr": " ولائم لي لم أحفل ملامته", "ajez": " ولا سمحت له مني بما طالبا"}, {"bayt": " قال اسل فالحب قد عناك قلت أجل حتى أراجع من لبي الذي عزبا", "sadr": " قال اسل فالحب قد عناك قلت أجل", "ajez": " حتى أراجع من لبي الذي عزبا"}, {"bayt": " طرفي الذي جلب البلوى إلى بدني فلمه دوني في الخطب الذي جلبا", "sadr": " طرفي الذي جلب البلوى إلى بدني", "ajez": " فلمه دوني في الخطب الذي جلبا"}, {"bayt": " هو الهوى وهو أني فيه محتمل ورب مر عذابي في الهوى عذبا", "sadr": " هو الهوى وهو أني فيه محتمل", "ajez": " ورب مر عذابي في الهوى عذبا"}, {"bayt": " أما ترى ابن علي حين تيمه حب العلا كيف لا يشكو له وصبا", "sadr": " أما ترى ابن علي حين تيمه", "ajez": " حب العلا كيف لا يشكو له وصبا"}, {"bayt": " أغر ما برحت تثني عزائمه سيف الهدى بنجيع الشرك مختضبا", "sadr": " أغر ما برحت تثني عزائمه", "ajez": " سيف الهدى بنجيع الشرك مختضبا"}, {"bayt": " قد أصبح الملك منه في يدي ملك مر الحفيظة يرضي الله أن غضبا", "sadr": " قد أصبح الملك منه في يدي ملك", "ajez": " مر الحفيظة يرضي الله أن غضبا"}, {"bayt": " لو أن أيسر جزء من محاسنه بالغيث ما كف أو بالبدر ما غربا", "sadr": " لو أن أيسر جزء من محاسنه", "ajez": " بالغيث ما كف أو بالبدر ما غربا"}], "era": "العصر الأندلسي", "title": "لم يدعني الشوق إلا اقتادني طربا"}