{"id": "22280", "author": "عبد الغفار الأخرس", "abyat": [{"bayt": " أتى ببراهين غدا كلُّ جاحدٍ ببرهانه بين البرية مفحما", "sadr": " أتى ببراهين غدا كلُّ جاحدٍ", "ajez": " ببرهانه بين البرية مفحما"}, {"bayt": " فألزمهُ بالحقّ والحقّ قوله فأسْلَمَ من بعد الجحود وسلّما", "sadr": " فألزمهُ بالحقّ والحقّ قوله", "ajez": " فأسْلَمَ من بعد الجحود وسلّما"}, {"bayt": " فطوراً تراه للأمور مسدّداً وطوراً تراه للعلوم معلما", "sadr": " فطوراً تراه للأمور مسدّداً", "ajez": " وطوراً تراه للعلوم معلما"}, {"bayt": " فلله ما صنّفت كل مصنّف سرى منجداً في العالمين ومتهما", "sadr": " فلله ما صنّفت كل مصنّف", "ajez": " سرى منجداً في العالمين ومتهما"}, {"bayt": " ومن مشكلات بالعلوم عرفتها فأعربت عما كان فيهن معجما", "sadr": " ومن مشكلات بالعلوم عرفتها", "ajez": " فأعربت عما كان فيهن معجما"}, {"bayt": " وأبكيت أقلام البراعة والنهى فأرضيت حد السيف حتى تبسما", "sadr": " وأبكيت أقلام البراعة والنهى", "ajez": " فأرضيت حد السيف حتى تبسما"}, {"bayt": " وما نلت عما شان بالمجد خالياً وما زلت بالعلم اللّدنيّ مفعما", "sadr": " وما نلت عما شان بالمجد خالياً", "ajez": " وما زلت بالعلم اللّدنيّ مفعما"}, {"bayt": " تفرَّدت في علم وفهم وحكمة فها أنت والعلياء أصبحت توأما", "sadr": " تفرَّدت في علم وفهم وحكمة", "ajez": " فها أنت والعلياء أصبحت توأما"}, {"bayt": " وإن جئتنا في آخر الدهر رحمة إذا عدَّت الأمجاد كنت المقدما", "sadr": " وإن جئتنا في آخر الدهر رحمة", "ajez": " إذا عدَّت الأمجاد كنت المقدما"}, {"bayt": " وحسبك ما في الناس مثلك سيد أنال مقلاً أو تكرّم معدما", "sadr": " وحسبك ما في الناس مثلك سيد", "ajez": " أنال مقلاً أو تكرّم معدما"}, {"bayt": " وكم نثرت نثراً بلاغتك التي أردت بها دُرَّ المعالي منظما", "sadr": " وكم نثرت نثراً بلاغتك التي", "ajez": " أردت بها دُرَّ المعالي منظما"}, {"bayt": " وقد أخرستني من علاك فصاحة ألبست تراني أخرس النطق أبكما", "sadr": " وقد أخرستني من علاك فصاحة", "ajez": " ألبست تراني أخرس النطق أبكما"}], "era": "العصر الأندلسي", "title": "أتى ببراهين غدا كلُّ جاحدٍ"}