{"id": "22580", "author": "عبد الغفار الأخرس", "abyat": [{"bayt": " ليهنكم العقدُ المبارك إنَّهُ عَلى  خير كُفْوٍ للكريم وأقرانِ", "sadr": " ليهنكم العقدُ المبارك إنَّهُ", "ajez": " عَلى  خير كُفْوٍ للكريم وأقرانِ"}, {"bayt": " ومجتمع الأشراف من كلّ وجهة أكابر ساداتٍ وأشراف أعيانِ", "sadr": " ومجتمع الأشراف من كلّ وجهة", "ajez": " أكابر ساداتٍ وأشراف أعيانِ"}, {"bayt": " وقد كنت أرجو الله من قبل هذه أرى  فيه ما أمَّلْتُه منذ أزمان", "sadr": " وقد كنت أرجو الله من قبل هذه", "ajez": " أرى  فيه ما أمَّلْتُه منذ أزمان"}, {"bayt": " وما زلتُ أدعو الله ما قد يسرّني بأبناء أصحابي الكرام وإخواني", "sadr": " وما زلتُ أدعو الله ما قد يسرّني", "ajez": " بأبناء أصحابي الكرام وإخواني"}, {"bayt": " فكان بحمد الله عقداً مباركاً جَلوباً لأفراحي سلوباً لأحزاني", "sadr": " فكان بحمد الله عقداً مباركاً", "ajez": " جَلوباً لأفراحي سلوباً لأحزاني"}, {"bayt": " سُرِرْنا وسُرَّ الناس فيما أتوا به بيوم له شأن وناهيك من شان", "sadr": " سُرِرْنا وسُرَّ الناس فيما أتوا به", "ajez": " بيوم له شأن وناهيك من شان"}, {"bayt": " ودام بخير للمسرات والهنا فأرَّخْتُ عَقْدُ الخير دام بنعمان", "sadr": " ودام بخير للمسرات والهنا", "ajez": " فأرَّخْتُ عَقْدُ الخير دام بنعمان"}], "era": "العصر الأندلسي", "title": "ليهنكم العقدُ المبارك إنَّهُ"}