{"id": "22753", "author": "حيدر بن سليمان الحلي", "abyat": [{"bayt": " قم ناشد الأسلام عن مصابه أصيب بالنبي أم كتابه\r", "sadr": " قم ناشد الأسلام عن مصابه", "ajez": " أصيب بالنبي أم كتابه\r"}, {"bayt": " أم أنَّ ركب الموت عنه قد سرى بالروح محمولا على ركابه\r", "sadr": " أم أنَّ ركب الموت عنه قد سرى", "ajez": " بالروح محمولا على ركابه\r"}, {"bayt": " بلى قضى نفسُ النبيّ المرتضى وأجدرج الليلة في أثوابه\r", "sadr": " بلى قضى نفسُ النبيّ المرتضى", "ajez": " وأجدرج الليلة في أثوابه\r"}, {"bayt": " مضى على اهتضامه بغضة غص بها الدهر مدى أحقابه\r", "sadr": " مضى على اهتضامه بغضة", "ajez": " غص بها الدهر مدى أحقابه\r"}, {"bayt": " عاش غريباً بينها وقد قضى بسيف أشقاها على اعترابه\r", "sadr": " عاش غريباً بينها وقد قضى", "ajez": " بسيف أشقاها على اعترابه\r"}, {"bayt": " لقد أراقوا ليلة القدر دماً دماؤها انصببن بانصبابه\r", "sadr": " لقد أراقوا ليلة القدر دماً", "ajez": " دماؤها انصببن بانصبابه\r"}, {"bayt": " تنزل الروح فوافى روحه صاعدة شوقاً إلى ثوابه\r", "sadr": " تنزل الروح فوافى روحه", "ajez": " صاعدة شوقاً إلى ثوابه\r"}, {"bayt": " فضج والاملاك فيها ضجة منها اقشعر الكون في إهابه\r", "sadr": " فضج والاملاك فيها ضجة", "ajez": " منها اقشعر الكون في إهابه\r"}, {"bayt": " وانقلب السلامُ للفجر بها للحشر إعوالاً على مُصابه\r", "sadr": " وانقلب السلامُ للفجر بها", "ajez": " للحشر إعوالاً على مُصابه\r"}, {"bayt": " الله نفس أحمد من قد غدا من نفص كل مؤمن \"أولى به\"\r", "sadr": " الله نفس أحمد من قد غدا", "ajez": " من نفص كل مؤمن \"أولى به\"\r"}, {"bayt": " غدره ابن ملجم ووجهه مُخضَّبٌ بالدم في محرابه\r", "sadr": " غدره ابن ملجم ووجهه", "ajez": " مُخضَّبٌ بالدم في محرابه\r"}, {"bayt": " وجه لوجه الله كم عفرت في مسجد كان \"أبا ترابه\"\r", "sadr": " وجه لوجه الله كم عفرت", "ajez": " في مسجد كان \"أبا ترابه\"\r"}, {"bayt": " فاغبر وجه الدين لا صفراره وخُضّب الإيمانُ لاختضابه\r", "sadr": " فاغبر وجه الدين لا صفراره", "ajez": " وخُضّب الإيمانُ لاختضابه\r"}, {"bayt": " ويزعمُون حيثُ طلّوا دمهُ في صومهم قد زيد في ثوابه\r", "sadr": " ويزعمُون حيثُ طلّوا دمهُ", "ajez": " في صومهم قد زيد في ثوابه\r"}, {"bayt": " والصوم يدعو كل عام صارخاً قد نضحوا دَمي على ثيابه\r", "sadr": " والصوم يدعو كل عام صارخاً", "ajez": " قد نضحوا دَمي على ثيابه\r"}, {"bayt": " إطاعة ٌ قتلُهم مَن لم يكن تُقبلُ طاعاتُ الورى إلاّ به\r", "sadr": " إطاعة ٌ قتلُهم مَن لم يكن", "ajez": " تُقبلُ طاعاتُ الورى إلاّ به\r"}, {"bayt": " قتلتُم الصلاة في محرابها ياقاتليه وهو في محرابه\r", "sadr": " قتلتُم الصلاة في محرابها", "ajez": " ياقاتليه وهو في محرابه\r"}, {"bayt": " وشق رأس العدل سيف جوركم مذشق منه الرأس في ذبابه\r", "sadr": " وشق رأس العدل سيف جوركم", "ajez": " مذشق منه الرأس في ذبابه\r"}, {"bayt": " فليبك \"جبريل\" له ولينتحب في الملأ الأعلى على مصابه\r", "sadr": " فليبك \"جبريل\" له ولينتحب", "ajez": " في الملأ الأعلى على مصابه\r"}, {"bayt": " نعم بكى والعيثُ من بُكائه ينحب والرعد من انتحابه\r", "sadr": " نعم بكى والعيثُ من بُكائه", "ajez": " ينحب والرعد من انتحابه\r"}, {"bayt": " منتدباً في صرخة ٍ وإنّما يستصرخُ «المهديّ» في انتدابه\r", "sadr": " منتدباً في صرخة ٍ وإنّما", "ajez": " يستصرخُ «المهديّ» في انتدابه\r"}, {"bayt": " ياأيها المجوب عن شيعته وكاشف الغُمّى على احتجابه\r", "sadr": " ياأيها المجوب عن شيعته", "ajez": " وكاشف الغُمّى على احتجابه\r"}, {"bayt": " كم تغمد السيف لقد تقطّعت رقابُ أهلِ الحق في ارتقابه\r", "sadr": " كم تغمد السيف لقد تقطّعت", "ajez": " رقابُ أهلِ الحق في ارتقابه\r"}, {"bayt": " فانهض لها فليس إلاك لها قد سئم الصابرُ جرع صابه\r", "sadr": " فانهض لها فليس إلاك لها", "ajez": " قد سئم الصابرُ جرع صابه\r"}, {"bayt": " واطلب اباك المرتضى ممن غدا مُنقلباً عنهُ على أَعقابه\r", "sadr": " واطلب اباك المرتضى ممن غدا", "ajez": " مُنقلباً عنهُ على أَعقابه\r"}, {"bayt": " وقل ولكن بلسان مرهف واجعل دماء القوم في جوابه:\r", "sadr": " وقل ولكن بلسان مرهف", "ajez": " واجعل دماء القوم في جوابه:\r"}, {"bayt": " يا عصبة الالحاد أين من قضى مُحتسباً وكنتِ في احتسابه\r", "sadr": " يا عصبة الالحاد أين من قضى", "ajez": " مُحتسباً وكنتِ في احتسابه\r"}, {"bayt": " أين أميرُ المؤمنين أوما عن قتله اكتفيت في اغتصابِه\r", "sadr": " أين أميرُ المؤمنين أوما", "ajez": " عن قتله اكتفيت في اغتصابِه\r"}, {"bayt": " لله كم جُرعة غيظٍ ساغها بعد نبيّ الله من أَصحابه\r", "sadr": " لله كم جُرعة غيظٍ ساغها", "ajez": " بعد نبيّ الله من أَصحابه\r"}, {"bayt": " وهي على العالم لو توزعت أشرقت العالم في شرابه\r", "sadr": " وهي على العالم لو توزعت", "ajez": " أشرقت العالم في شرابه\r"}, {"bayt": " فانع إلى أحمد ثقل أحمد وقُل له يا خير مَن يُدعى به\r", "sadr": " فانع إلى أحمد ثقل أحمد", "ajez": " وقُل له يا خير مَن يُدعى به\r"}, {"bayt": " إنَّ الأُلى على النفاقِ مَرَدوا قد كشفوا بَعدك عن نِقابِه\r", "sadr": " إنَّ الأُلى على النفاقِ مَرَدوا", "ajez": " قد كشفوا بَعدك عن نِقابِه\r"}, {"bayt": " وصيروا سرح الهدى فريسة للغيِّ بين الطلسِ من ذِيابه\r", "sadr": " وصيروا سرح الهدى فريسة", "ajez": " للغيِّ بين الطلسِ من ذِيابه\r"}, {"bayt": " وغادروا حقَّ أخيك مُضغة ً يلوكها الباطلُ في أنيابِه\r", "sadr": " وغادروا حقَّ أخيك مُضغة ً", "ajez": " يلوكها الباطلُ في أنيابِه\r"}, {"bayt": " وظلَّ راعي إفكهم يحلبُ مِن ضرع لبون الجور في وطابه\r", "sadr": " وظلَّ راعي إفكهم يحلبُ مِن", "ajez": " ضرع لبون الجور في وطابه\r"}, {"bayt": " فالأمة اليوم غدت في مجهل مذ قتلوا الهادي الذي تهدى به\r", "sadr": " فالأمة اليوم غدت في مجهل", "ajez": " مذ قتلوا الهادي الذي تهدى به\r"}, {"bayt": " لم يتشعَّب في قريشِ نسبٌ إلاّ غَدا في المحضِ مِن لُبابه\r", "sadr": " لم يتشعَّب في قريشِ نسبٌ", "ajez": " إلاّ غَدا في المحضِ مِن لُبابه\r"}, {"bayt": " حتى أتيت فأتى في حسب قد دخل التنزيل في حسابه\r", "sadr": " حتى أتيت فأتى في حسب", "ajez": " قد دخل التنزيل في حسابه\r"}, {"bayt": " فيالها غلطة دهر بعدها لا يَحمدُ الدهر على صوابِه\r", "sadr": " فيالها غلطة دهر بعدها", "ajez": " لا يَحمدُ الدهر على صوابِه\r"}, {"bayt": " مشى إلى خُلفِ بها فأَصبحت أَرؤُسهُ تتبع من أَذنابِه\r", "sadr": " مشى إلى خُلفِ بها فأَصبحت", "ajez": " أَرؤُسهُ تتبع من أَذنابِه\r"}, {"bayt": " وما كفاه أن أرانا ضلة وِهادُه تعلو على هِضابه\r", "sadr": " وما كفاه أن أرانا ضلة", "ajez": " وِهادُه تعلو على هِضابه\r"}, {"bayt": " حتى أرانا ذئبَه مُفترساً بين الشبول ليثه في غابه\r", "sadr": " حتى أرانا ذئبَه مُفترساً", "ajez": " بين الشبول ليثه في غابه\r"}, {"bayt": " هذا أمسر المؤمنين بعدما ألجأهم للدين في ضِرابه\r", "sadr": " هذا أمسر المؤمنين بعدما", "ajez": " ألجأهم للدين في ضِرابه\r"}, {"bayt": " وقادَ من عُتاتِهم مَصاعباً ما أسمَحت لولا شبا قِرضابِه\r", "sadr": " وقادَ من عُتاتِهم مَصاعباً", "ajez": " ما أسمَحت لولا شبا قِرضابِه\r"}, {"bayt": " قد أَلفَ الهيجاءَ حتى ليلها غرابه يأنس في عقابه\r", "sadr": " قد أَلفَ الهيجاءَ حتى ليلها", "ajez": " غرابه يأنس في عقابه\r"}, {"bayt": " يمشي إليها وهوَ في ذِهابِه أشد شوقاً منه في غيابه\r", "sadr": " يمشي إليها وهوَ في ذِهابِه", "ajez": " أشد شوقاً منه في غيابه\r"}, {"bayt": " كالشبل في وثبته والسيف في هبته والصل في انسيابه\r", "sadr": " كالشبل في وثبته والسيف في", "ajez": " هبته والصل في انسيابه\r"}, {"bayt": " أرداهُ من لو لَحظته عينُه في مأزق لفر من إرهابه\r", "sadr": " أرداهُ من لو لَحظته عينُه", "ajez": " في مأزق لفر من إرهابه\r"}, {"bayt": " ومر من بين الجوع هارباً يود أن يخرج من إهابه\r", "sadr": " ومر من بين الجوع هارباً", "ajez": " يود أن يخرج من إهابه\r"}, {"bayt": " وهوَ لعمري لو يشاءُ لَم يَنل ما نال أشق القوم في آرابه\r", "sadr": " وهوَ لعمري لو يشاءُ لَم يَنل", "ajez": " ما نال أشق القوم في آرابه\r"}, {"bayt": " لكن غدا مُسلِّماً مُحتسِباً والخير كل الخير في احتسابه\r", "sadr": " لكن غدا مُسلِّماً مُحتسِباً", "ajez": " والخير كل الخير في احتسابه\r"}, {"bayt": " صلّى عليه الله من مضطهدٍ قد أغضبوا الرحمن في اغتصابِه", "sadr": " صلّى عليه الله من مضطهدٍ", "ajez": " قد أغضبوا الرحمن في اغتصابِه"}], "era": "العصر الأندلسي", "title": "قم ناشد الأسلام عن مصابه"}