{"id": "57279", "author": "ابن زمرك", "abyat": [{"bayt": " في كؤوس الثغر من ذاك اللعس راحة الأرواح", "sadr": " في كؤوس الثغر من ذاك اللعس", "ajez": " راحة الأرواح"}, {"bayt": " وتغشى الروض مسكي النفس عاطر الارواح", "sadr": " وتغشى الروض مسكي النفس", "ajez": " عاطر الارواح"}, {"bayt": " وكسا الأرواح وشيا مذهبا يبهر الشمسا", "sadr": " وكسا الأرواح وشيا مذهبا", "ajez": " يبهر الشمسا"}, {"bayt": " عسجد قد حل من فوق الربى يبهج النفسا", "sadr": " عسجد قد حل من فوق الربى", "ajez": " يبهج النفسا"}, {"bayt": " فاتخذ للهو فيه مركبا تلحق الأنسا", "sadr": " فاتخذ للهو فيه مركبا", "ajez": " تلحق الأنسا"}, {"bayt": " منبر الغصن عليه قد جلس ساجع الادواح", "sadr": " منبر الغصن عليه قد جلس", "ajez": " ساجع الادواح"}, {"bayt": " حلل السندس خضرا قد لبس عطفه المرتاح", "sadr": " حلل السندس خضرا قد لبس", "ajez": " عطفه المرتاح"}, {"bayt": " قم ترى هذا الأصيل شاحبا حسنه قد راق", "sadr": " قم ترى هذا الأصيل شاحبا", "ajez": " حسنه قد راق"}, {"bayt": " ولأذيال الغصون ساحبا في حلى الأوراق", "sadr": " ولأذيال الغصون ساحبا", "ajez": " في حلى الأوراق"}, {"bayt": " ونديم قال لي مخاطبا قول ذي إشفاق", "sadr": " ونديم قال لي مخاطبا", "ajez": " قول ذي إشفاق"}, {"bayt": " عادة الشمس بغرب تختلس هات شمس الراح", "sadr": " عادة الشمس بغرب تختلس", "ajez": " هات شمس الراح"}, {"bayt": " إن أرانا الجو وجها قد عبس أوقد المصباح", "sadr": " إن أرانا الجو وجها قد عبس", "ajez": " أوقد المصباح"}, {"bayt": " ووجوه الشرب تغني عن شموس كلما تجلى", "sadr": " ووجوه الشرب تغني عن شموس", "ajez": " كلما تجلى"}, {"bayt": " بلحاظ اسكرتنا عن كؤوس خمرها أحلى", "sadr": " بلحاظ اسكرتنا عن كؤوس", "ajez": " خمرها أحلى"}, {"bayt": " مظهرات من خفايا في النفوس سورا تتلى", "sadr": " مظهرات من خفايا في النفوس", "ajez": " سورا تتلى"}, {"bayt": " ما زمان الأنس إلا مختلس فاغتنم يا صاح", "sadr": " ما زمان الأنس إلا مختلس", "ajez": " فاغتنم يا صاح"}, {"bayt": " وعيون الشهب تذكى عن حرس تخصم النصاح", "sadr": " وعيون الشهب تذكى عن حرس", "ajez": " تخصم النصاح"}, {"bayt": " ما ترى ثغر الوميض باسما يظهر البشرا", "sadr": " ما ترى ثغر الوميض باسما", "ajez": " يظهر البشرا"}, {"bayt": " وثناء الروض هب ناسما عاطرا نشرا", "sadr": " وثناء الروض هب ناسما", "ajez": " عاطرا نشرا"}, {"bayt": " بث من أزهاره دراهما قائلا بشرى", "sadr": " بث من أزهاره دراهما", "ajez": " قائلا بشرى"}, {"bayt": " ركب المولى مع الظهر الفرس وشفي وارتاح", "sadr": " ركب المولى مع الظهر الفرس", "ajez": " وشفي وارتاح"}, {"bayt": " بجنود الله دأبا يحترس إن غدا أو راح", "sadr": " بجنود الله دأبا يحترس", "ajez": " إن غدا أو راح"}, {"bayt": " وجب الشكر علينا والهنا بعضنا بعضا", "sadr": " وجب الشكر علينا والهنا", "ajez": " بعضنا بعضا"}, {"bayt": " فزمان السعد وضاح السنا وجهه الأرضي", "sadr": " فزمان السعد وضاح السنا", "ajez": " وجهه الأرضي"}, {"bayt": " اثمرت فيه العوالي بالمنى ثمرا غضا", "sadr": " اثمرت فيه العوالي بالمنى", "ajez": " ثمرا غضا"}, {"bayt": " يجتني الإسلام منها ما اغترس سيفه السفاح", "sadr": " يجتني الإسلام منها ما اغترس", "ajez": " سيفه السفاح"}, {"bayt": " في ضمير النقع منها قد هجس شهب تلتاح", "sadr": " في ضمير النقع منها قد هجس", "ajez": " شهب تلتاح"}, {"bayt": " يا إماما بالحسام المنتضى نصر الحقا", "sadr": " يا إماما بالحسام المنتضى", "ajez": " نصر الحقا"}, {"bayt": " ثغرك الوضاح مهما اومضا أخجل البرقا", "sadr": " ثغرك الوضاح مهما اومضا", "ajez": " أخجل البرقا"}, {"bayt": " وديون السعد منه تقتضى توسع الحقا", "sadr": " وديون السعد منه تقتضى", "ajez": " توسع الحقا"}, {"bayt": " لك وجه من صباح مقتبس بشره وضاح", "sadr": " لك وجه من صباح مقتبس", "ajez": " بشره وضاح"}, {"bayt": " وجميل الصفح منه ملتمس منعم صفاح", "sadr": " وجميل الصفح منه ملتمس", "ajez": " منعم صفاح"}, {"bayt": " هاكها تمزج لطفا بالنسيم كلما هبا", "sadr": " هاكها تمزج لطفا بالنسيم", "ajez": " كلما هبا"}, {"bayt": " قد أتت بالبر والصنع الجسيم تشكر الربا", "sadr": " قد أتت بالبر والصنع الجسيم", "ajez": " تشكر الربا"}, {"bayt": " أخجلت من قال في الصبح الوسيم مغرما صبا", "sadr": " أخجلت من قال في الصبح الوسيم", "ajez": " مغرما صبا"}, {"bayt": " غرد الطير فنبه من نعس يا مدير الراح", "sadr": " غرد الطير فنبه من نعس", "ajez": " يا مدير الراح"}, {"bayt": " وتعرى الفجر عن ثوب الغلس وانجلى الإصباح", "sadr": " وتعرى الفجر عن ثوب الغلس", "ajez": " وانجلى الإصباح"}], "era": "العصر الأندلسي", "title": "في كؤوس الثغر من ذاك اللعس"}