{"id": "57277", "author": "ابن زمرك", "abyat": [{"bayt": " مولاي مولاي وأنت الذي جددت للأملاك عهد الجلال", "sadr": " مولاي مولاي وأنت الذي", "ajez": " جددت للأملاك عهد الجلال"}, {"bayt": " والشمس والبدر من العوذ لما رأت منك بديع الجمال", "sadr": " والشمس والبدر من العوذ", "ajez": " لما رأت منك بديع الجمال"}, {"bayt": " والروض في نعمته يغتذي بطيب ما قد حزته من خلال", "sadr": " والروض في نعمته يغتذي", "ajez": " بطيب ما قد حزته من خلال"}, {"bayt": " بشراك بشراك بحسن المآب تستضحك الروض بثغر شنيب", "sadr": " بشراك بشراك بحسن المآب", "ajez": " تستضحك الروض بثغر شنيب"}, {"bayt": " ودمت محروس العلا والجناب بعصمة الله السميع المجيب", "sadr": " ودمت محروس العلا والجناب", "ajez": " بعصمة الله السميع المجيب"}], "era": "العصر الأندلسي", "title": "مولاي مولاي وأنت الذي"}