{"id": "70016", "author": "عدي بن زيد", "abyat": [{"bayt": " وَيحَ عَمرِو بنِ عَدِيٍّ مِن رَجُل    خانَ يَوماً بَعدَ ما قيلَ كَمَل\r", "sadr": " وَيحَ عَمرِو بنِ عَدِيٍّ مِن رَجُل", "ajez": "    خانَ يَوماً بَعدَ ما قيلَ كَمَل\r"}, {"bayt": " كانَ لا يَعقِلُ حَتّى ما إِذا      جاءَ يَومٌ يَأكُلُ الناسَ عَقَل\r", "sadr": " كانَ لا يَعقِلُ حَتّى ما إِذا", "ajez": "      جاءَ يَومٌ يَأكُلُ الناسَ عَقَل\r"}, {"bayt": " أَبِهِم دَلاكَ عَمرٌو لِلرَدى    وَقَديماً حينَ لِلمَرءِ الأَجَل\r", "sadr": " أَبِهِم دَلاكَ عَمرٌو لِلرَدى", "ajez": "    وَقَديماً حينَ لِلمَرءِ الأَجَل\r"}, {"bayt": " لَيتَ نُعمانَ عَلَينا مَلِكٌ    وَبُنَيٌّ لِيَ حَيٌّ لَم يَزَل\r", "sadr": " لَيتَ نُعمانَ عَلَينا مَلِكٌ", "ajez": "    وَبُنَيٌّ لِيَ حَيٌّ لَم يَزَل\r"}, {"bayt": " قَد تَنَظَّرنا لِغادٍ أَوبَةً   كانَ لَو يُغني عَنِ المَرءِ الأَمَل\r", "sadr": " قَد تَنَظَّرنا لِغادٍ أَوبَةً", "ajez": "   كانَ لَو يُغني عَنِ المَرءِ الأَمَل\r"}, {"bayt": " بانَ مَعهُ عَضُدٌ مَع ساعِدٍ بُؤسا لِلدَهرِ وَبُؤسا لِلرَجُل", "sadr": " بانَ مَعهُ عَضُدٌ مَع ساعِدٍ", "ajez": " بُؤسا لِلدَهرِ وَبُؤسا لِلرَجُل"}], "era": "العصر الجاهلي", "title": "ويح عمرِو بن عدي من رجل"}