{"id": "15471", "author": "ابن الفارض", "abyat": [{"bayt": " نشرتُ في موكبِ العشَّاقِ أعلامي وكانَ قبلي بُلى في الحبِّ أغلامي", "sadr": " نشرتُ في موكبِ العشَّاقِ أعلامي", "ajez": " وكانَ قبلي بُلى في الحبِّ أغلامي"}, {"bayt": " وسِرْتُ فيهِ ولم أبْرَحْ بِدَوْلَتِهِ، حتى وَجَدْتُ مُلوكَ العِشقِ خُدّامي", "sadr": " وسِرْتُ فيهِ ولم أبْرَحْ بِدَوْلَتِهِ،", "ajez": " حتى وَجَدْتُ مُلوكَ العِشقِ خُدّامي"}, {"bayt": " ولمْ أزلْ منذُ أخذِ العهدِ في قدمي لكَعْبَة ِ الحُسنِ، تجريدي وإحرامي", "sadr": " ولمْ أزلْ منذُ أخذِ العهدِ في قدمي", "ajez": " لكَعْبَة ِ الحُسنِ، تجريدي وإحرامي"}, {"bayt": " وقد رَماني هَواكُم في الغَرامِ إلى مقامِ حبٍّ شريفٍ شامخٍ سامِ", "sadr": " وقد رَماني هَواكُم في الغَرامِ إلى", "ajez": " مقامِ حبٍّ شريفٍ شامخٍ سامِ"}, {"bayt": " جهلتُ أهليَ فيهِ أهلَ نسبتهِ وهمْ أعزُّ أخلاَّئي وألزامي", "sadr": " جهلتُ أهليَ فيهِ أهلَ نسبتهِ", "ajez": " وهمْ أعزُّ أخلاَّئي وألزامي"}, {"bayt": " قضيتُ فيهِ إلى حين انقضا أجلي شهري ودهري وساعاتي وأعوامي", "sadr": " قضيتُ فيهِ إلى حين انقضا أجلي", "ajez": " شهري ودهري وساعاتي وأعوامي"}, {"bayt": " ظنَّ  العذولُ بأنًّ العذلَ يوقفني نامَ العذولُ وشوقي زائدُ نامِ", "sadr": " ظنَّ  العذولُ بأنًّ العذلَ يوقفني", "ajez": " نامَ العذولُ وشوقي زائدُ نامِ"}, {"bayt": " إن عامَ إنسانُ عَيني في مَدامِعِهِ، فقدْ أُمِدّ بإحْسانٍ وإنعامِ", "sadr": " إن عامَ إنسانُ عَيني في مَدامِعِهِ،", "ajez": " فقدْ أُمِدّ بإحْسانٍ وإنعامِ"}, {"bayt": " يا سائقاً عيسَ أحبابي عسى مهلاً وسرْ رُوَيْداً، فقَلبي بينَ أنْعامِ", "sadr": " يا سائقاً عيسَ أحبابي عسى مهلاً", "ajez": " وسرْ رُوَيْداً، فقَلبي بينَ أنْعامِ"}, {"bayt": " سَلَكْتُ كُلّ مَقامٍ في مَحَبّتِكُمْ وما تَرَكْتُ مَقاماً قَطّ قُدّامي", "sadr": " سَلَكْتُ كُلّ مَقامٍ في مَحَبّتِكُمْ", "ajez": " وما تَرَكْتُ مَقاماً قَطّ قُدّامي"}, {"bayt": " وكُنتُ أحْسَبُ أنّي قد وَصَلْتُ إلى أعْلى ، وأغْلى مَقامٍ، بينَ أقْوامي", "sadr": " وكُنتُ أحْسَبُ أنّي قد وَصَلْتُ إلى", "ajez": " أعْلى ، وأغْلى مَقامٍ، بينَ أقْوامي"}, {"bayt": " حتى بَدا لي مَقامٌ لم يكُنْ أرَبي، ولمْ يمرَّ بأفكاري وأوهامي", "sadr": " حتى بَدا لي مَقامٌ لم يكُنْ أرَبي،", "ajez": " ولمْ يمرَّ بأفكاري وأوهامي"}, {"bayt": " إنْ كانَ منزلتي في الحبِّ عندكمْ ما قد رأيتُ، فقد ضَيّعْتُ أيّامي", "sadr": " إنْ كانَ منزلتي في الحبِّ عندكمْ", "ajez": " ما قد رأيتُ، فقد ضَيّعْتُ أيّامي"}, {"bayt": " أمنيَّة ٌ ظفرتْ روحي بها زمناً واليومَ أحسَبُها أضغاثَ أحْلامِ", "sadr": " أمنيَّة ٌ ظفرتْ روحي بها زمناً", "ajez": " واليومَ أحسَبُها أضغاثَ أحْلامِ"}, {"bayt": " وإنْ يكنْ فرطُ وجدي في محبَّتكمْ إثماً فقدْ كثرتْ في الحبِّ آثامي", "sadr": " وإنْ يكنْ فرطُ وجدي في محبَّتكمْ", "ajez": " إثماً فقدْ كثرتْ في الحبِّ آثامي"}, {"bayt": " ولو عَلِمْتُ بأنّ الحُبّ آخِرُهُ هذا الحِمامُ، لَما خالَفْتُ لُوّامي", "sadr": " ولو عَلِمْتُ بأنّ الحُبّ آخِرُهُ", "ajez": " هذا الحِمامُ، لَما خالَفْتُ لُوّامي"}, {"bayt": " أوْدَعْتُ قلبي إلى مَن ليس يَحفَظُهُ أبْصرْتُ خلفي، وما طالَعتُ قٌدّامي", "sadr": " أوْدَعْتُ قلبي إلى مَن ليس يَحفَظُهُ", "ajez": " أبْصرْتُ خلفي، وما طالَعتُ قٌدّامي"}, {"bayt": " لقدْ رماني بسهمٍ من لواحظهِ أصْمى فؤادي، فواشوقي إلى الرامي", "sadr": " لقدْ رماني بسهمٍ من لواحظهِ", "ajez": " أصْمى فؤادي، فواشوقي إلى الرامي"}, {"bayt": " آهاً على نَظرَة ٍ مِنْهُ أُسَرّ بها، فإنَّ أقصى مرامي رؤية ُ الرَّامي", "sadr": " آهاً على نَظرَة ٍ مِنْهُ أُسَرّ بها،", "ajez": " فإنَّ أقصى مرامي رؤية ُ الرَّامي"}, {"bayt": " إنْ أسْعَدَ اللّهُ روحي، في محَبّتِهِ، وجسمها بينَ أرواحٍ وأجسامِ", "sadr": " إنْ أسْعَدَ اللّهُ روحي، في محَبّتِهِ،", "ajez": " وجسمها بينَ أرواحٍ وأجسامِ"}, {"bayt": " وشاهدتْ واجتلتْ وجهَ الحبيبِ فما أسى وأسعدَ أرزاقي وأقسامي", "sadr": " وشاهدتْ واجتلتْ وجهَ الحبيبِ فما", "ajez": " أسى وأسعدَ أرزاقي وأقسامي"}, {"bayt": " ها قدأظَلّ زمانُ الوَصْلِ، يا أمَلي، فامنُنْ، وثَبّتْ بهِ قَلبي وأقدامي", "sadr": " ها قدأظَلّ زمانُ الوَصْلِ، يا أمَلي،", "ajez": " فامنُنْ، وثَبّتْ بهِ قَلبي وأقدامي"}, {"bayt": " وقد قَدِمتُ، وماقدّمتُ لي عَمَلاً، إلاّ غَرامي، وأشواقي، وإقدامي", "sadr": " وقد قَدِمتُ، وماقدّمتُ لي عَمَلاً،", "ajez": " إلاّ غَرامي، وأشواقي، وإقدامي"}, {"bayt": " دارُ السَّلامِ إليها قدْ وصلتُ إذنْ منْ سبلِ أبوابِ إيماني وإسلامي", "sadr": " دارُ السَّلامِ إليها قدْ وصلتُ إذنْ", "ajez": " منْ سبلِ أبوابِ إيماني وإسلامي"}, {"bayt": " يا ربَّنا أرني أنظرُ إليكَ بها عِندَ القُدومِ، وعامِلني بإكرْامِ", "sadr": " يا ربَّنا أرني أنظرُ إليكَ بها", "ajez": " عِندَ القُدومِ، وعامِلني بإكرْامِ"}], "era": "العصر العباسي", "title": "نشرتُ في موكبِ العشَّاقِ أعلامي"}