{"id": "26514", "author": "سبط ابن التعاويذي", "abyat": [{"bayt": " كذا كلَّ يومٍ دَولة ٌ تَتجَدَّدُ وَمُلْكٌ عَلَى رَغْمِ کلأَعَادِي مُخَلَّدُ", "sadr": " كذا كلَّ يومٍ دَولة ٌ تَتجَدَّدُ", "ajez": " وَمُلْكٌ عَلَى رَغْمِ کلأَعَادِي مُخَلَّدُ"}, {"bayt": " وجَدٌّ على ظهرِ المَجَرَّة ِ صاعدٌ وَمَجْدٌ عَلَى هَامِ کلنُّجُومِ مُوَطَّدُ", "sadr": " وجَدٌّ على ظهرِ المَجَرَّة ِ صاعدٌ", "ajez": " وَمَجْدٌ عَلَى هَامِ کلنُّجُومِ مُوَطَّدُ"}, {"bayt": " ولا زالَ للعافِينَ في كلِّ مَوسِمٍ وُقوفٌ على أبوابِكُمْ وتَردُّدُ", "sadr": " ولا زالَ للعافِينَ في كلِّ مَوسِمٍ", "ajez": " وُقوفٌ على أبوابِكُمْ وتَردُّدُ"}, {"bayt": " يَزُورُكُمُ فِيهَا کلتَّهَانِي وَشَمْلُكُمْ جميعٌ وشَملُ الحاسِدينَ مُبدَّدُ", "sadr": " يَزُورُكُمُ فِيهَا کلتَّهَانِي وَشَمْلُكُمْ", "ajez": " جميعٌ وشَملُ الحاسِدينَ مُبدَّدُ"}, {"bayt": " يَعُودُ إلَيْكُمْ بکلْبَقَاءِ وَعَيْشْكُمْ رقيقُ الحواشي وارِفُ الظلِّ أَغْيَدُ", "sadr": " يَعُودُ إلَيْكُمْ بکلْبَقَاءِ وَعَيْشْكُمْ", "ajez": " رقيقُ الحواشي وارِفُ الظلِّ أَغْيَدُ"}, {"bayt": "فَلاَ بَرِحَتْ تُهْدِي کلثَّنَاءَ إلَيْكُمُفَلاَ بَرِحَتْ تُهْدِي کلثَّنَاءَ إلَيْكُمُ", "sadr": "فَلاَ بَرِحَتْ تُهْدِي کلثَّنَاءَ إلَيْكُمُ", "ajez": "فَلاَ بَرِحَتْ تُهْدِي کلثَّنَاءَ إلَيْكُمُ"}], "era": "العصر العباسي", "title": "كذا كلَّ يومٍ دَولة ٌ تَتجَدَّدُ"}