{"id": "9824", "author": "الشريف الرضي", "abyat": [{"bayt": " ما يَصْنَعُ السّيرُ بالجُرْدِ السّرَاحِيبِ إنْ كانَ وَعدُ الأماني غيرَ مَكذوبِ", "sadr": " ما يَصْنَعُ السّيرُ بالجُرْدِ السّرَاحِيبِ", "ajez": " إنْ كانَ وَعدُ الأماني غيرَ مَكذوبِ"}, {"bayt": " لله أمر من الأيام اطلبه هيهات أطلب أمراً غير مطلوب", "sadr": " لله أمر من الأيام اطلبه", "ajez": " هيهات أطلب أمراً غير مطلوب"}, {"bayt": " لا تَصْحَبِ الدّهرَ إلاّ غيرَ مُنتَظِرٍ فالهم يطرده قرع الظنابيب", "sadr": " لا تَصْحَبِ الدّهرَ إلاّ غيرَ مُنتَظِرٍ", "ajez": " فالهم يطرده قرع الظنابيب"}, {"bayt": " وَاقذِفْ بنَفسِكَ في شَعوَاءَ خابِطَة ٍ كالسيل يعصف بالصوان واللوب", "sadr": " وَاقذِفْ بنَفسِكَ في شَعوَاءَ خابِطَة ٍ", "ajez": " كالسيل يعصف بالصوان واللوب"}, {"bayt": " إن حنت النيب شوقاً وهي واقفة فان عزمي مشتاق إلى النيب", "sadr": " إن حنت النيب شوقاً وهي واقفة", "ajez": " فان عزمي مشتاق إلى النيب"}, {"bayt": " أوْ صَارَتِ البِيضُ في الأغمادِ آجِنَة ً فإنما الضرب ماء غير مشروب", "sadr": " أوْ صَارَتِ البِيضُ في الأغمادِ آجِنَة ً", "ajez": " فإنما الضرب ماء غير مشروب"}, {"bayt": " مَتَى أرَاني وَدِرْعي غَيرُ مُحقَبَة ٍ أجر رمحي وسيفي غير مقروب", "sadr": " مَتَى أرَاني وَدِرْعي غَيرُ مُحقَبَة ٍ", "ajez": " أجر رمحي وسيفي غير مقروب"}, {"bayt": " أيد تجانب دنيا  لا بقاء لها خِبَاؤهَا بَينَ تَقْوِيضٍ وَتَطنِيبِ", "sadr": " أيد تجانب دنيا  لا بقاء لها", "ajez": " خِبَاؤهَا بَينَ تَقْوِيضٍ وَتَطنِيبِ"}, {"bayt": " قد كنت غراً وكان الدهر يسمح لي إن الرقيب على دنياي تجريبي", "sadr": " قد كنت غراً وكان الدهر يسمح لي", "ajez": " إن الرقيب على دنياي تجريبي"}, {"bayt": " وعدت يا دهر شيئاً بت أرقبه وما أرى منك إلا وعد عرقوب", "sadr": " وعدت يا دهر شيئاً بت أرقبه", "ajez": " وما أرى منك إلا وعد عرقوب"}, {"bayt": " وَحَاجَة ٍ أتَقَاضَاهَا وَتَمْطُلُني كَأنّهَا حَاجَة ٌ في نَفْسِ يَعقُوبِ", "sadr": " وَحَاجَة ٍ أتَقَاضَاهَا وَتَمْطُلُني", "ajez": " كَأنّهَا حَاجَة ٌ في نَفْسِ يَعقُوبِ"}, {"bayt": " لأُتْعِبَنّ عَلى البَيْداءِ رَاحِلَة ً والليل بالريح خفاق الجلابيب", "sadr": " لأُتْعِبَنّ عَلى البَيْداءِ رَاحِلَة ً", "ajez": " والليل بالريح خفاق الجلابيب"}, {"bayt": " ما كنتُ أرْغَبُ عن هوْجاءَ تَقذِفُ بي هام المرورى وأعناق الشناخيب", "sadr": " ما كنتُ أرْغَبُ عن هوْجاءَ تَقذِفُ بي", "ajez": " هام المرورى وأعناق الشناخيب"}, {"bayt": " في فِتية ٍ هَجرُوا الأوْطانَ وَاصْطَنَعوا إيدِي المَطَايَا بإدْلاجٍ وَتَأوِيبِ", "sadr": " في فِتية ٍ هَجرُوا الأوْطانَ وَاصْطَنَعوا", "ajez": " إيدِي المَطَايَا بإدْلاجٍ وَتَأوِيبِ"}, {"bayt": " مِنْ كلّ أشعَثَ مُلتاثِ اللّثَامِ، لَهُ لَحْظٌ تَكَرّرُهُ أجفَانُ مَدْؤوبِ", "sadr": " مِنْ كلّ أشعَثَ مُلتاثِ اللّثَامِ، لَهُ", "ajez": " لَحْظٌ تَكَرّرُهُ أجفَانُ مَدْؤوبِ"}, {"bayt": " يُوَسِّدُ الرّحْلَ خَدّاً مَا تَوَسّدَهُ قَبلَ المَطالبِ غيرُ الحُسنِ وَالطّيبِ", "sadr": " يُوَسِّدُ الرّحْلَ خَدّاً مَا تَوَسّدَهُ", "ajez": " قَبلَ المَطالبِ غيرُ الحُسنِ وَالطّيبِ"}, {"bayt": " إلَيكَ طارَتْ بِنا نُجْبٌ مُدَفَّعَة ٌ تحت السياط رميضات العراقيب", "sadr": " إلَيكَ طارَتْ بِنا نُجْبٌ مُدَفَّعَة ٌ", "ajez": " تحت السياط رميضات العراقيب"}, {"bayt": " وردن منك سحاباً غير منتقل عَنِ البِلادِ، وَبَدْراً غَيرَ مَحجوبِ", "sadr": " وردن منك سحاباً غير منتقل", "ajez": " عَنِ البِلادِ، وَبَدْراً غَيرَ مَحجوبِ"}, {"bayt": " مَا زِلْتَ تَرْغَبُ في مَجْدٍ تُشَيّدُهُ عَفْواً وَغَيرُكَ في كَدٍّ وَتَعذِيبِ", "sadr": " مَا زِلْتَ تَرْغَبُ في مَجْدٍ تُشَيّدُهُ", "ajez": " عَفْواً وَغَيرُكَ في كَدٍّ وَتَعذِيبِ"}, {"bayt": " حتى بَلَغْتَ مِنَ العَلْيَاءِ مَنْزِلَة ً تفدي الأعاجم فيها بالأعاريب", "sadr": " حتى بَلَغْتَ مِنَ العَلْيَاءِ مَنْزِلَة ً", "ajez": " تفدي الأعاجم فيها بالأعاريب"}, {"bayt": " إني رأيتك ممن لا يخادعه حَثُّ الزّجَاجَة ِ بالغِيدِ الرّعَابيبِ", "sadr": " إني رأيتك ممن لا يخادعه", "ajez": " حَثُّ الزّجَاجَة ِ بالغِيدِ الرّعَابيبِ"}, {"bayt": " ولا تحل يد الإقداح حبونه اذا  احتبى بين مطعون ومضروب", "sadr": " ولا تحل يد الإقداح حبونه", "ajez": " اذا  احتبى بين مطعون ومضروب"}, {"bayt": " يُهَابُ سَيفُكَ مَصْقولاً وَمُختَضِباً وأهيب الشعر شيب غير مخضوب", "sadr": " يُهَابُ سَيفُكَ مَصْقولاً وَمُختَضِباً", "ajez": " وأهيب الشعر شيب غير مخضوب"}, {"bayt": " يأوي حسامك إن صاح الضراب به الى لواءٍ من العلياء منصوب", "sadr": " يأوي حسامك إن صاح الضراب به", "ajez": " الى لواءٍ من العلياء منصوب"}, {"bayt": " وَيَرْتَمي بكَ، وَالأرْمَاحُ وَالِغَة ٌ طماح كل اسيل الخد  يعبوب", "sadr": " وَيَرْتَمي بكَ، وَالأرْمَاحُ وَالِغَة ٌ", "ajez": " طماح كل اسيل الخد  يعبوب"}, {"bayt": " بلم يسل همك من مال تفرقه إلاّ تَعَشّقَ أطْرَافَ الأنَابِيبِ", "sadr": " بلم يسل همك من مال تفرقه", "ajez": " إلاّ تَعَشّقَ أطْرَافَ الأنَابِيبِ"}, {"bayt": " إذا مَنَحْتَ العَوَالي كَفَّ مُسْتَلِبٍ أقطَعتَ بَذْلَ العَطايا كَفَّ مَسلوبِ", "sadr": " إذا مَنَحْتَ العَوَالي كَفَّ مُسْتَلِبٍ", "ajez": " أقطَعتَ بَذْلَ العَطايا كَفَّ مَسلوبِ"}, {"bayt": " لا يَرْكَبُ النّدبُ إلاّ كلَّ مُعضِلَة ٍ كَأنّ ظَهْرَ الهُوَيْنَا غَيرُ مَرْكوبِ", "sadr": " لا يَرْكَبُ النّدبُ إلاّ كلَّ مُعضِلَة ٍ", "ajez": " كَأنّ ظَهْرَ الهُوَيْنَا غَيرُ مَرْكوبِ"}, {"bayt": " ولا يرى الغدر اهلاً ان يلم به وانما الغدر مأخوذ عن الذيب", "sadr": " ولا يرى الغدر اهلاً ان يلم به", "ajez": " وانما الغدر مأخوذ عن الذيب"}, {"bayt": " مَا نَالَ مَدْحي أبُو نَصْرٍ بِنَائِلَة ٍ ولا بسلطان ترغيب وترهيب", "sadr": " مَا نَالَ مَدْحي أبُو نَصْرٍ بِنَائِلَة ٍ", "ajez": " ولا بسلطان ترغيب وترهيب"}, {"bayt": " إلاّ بِشيمَة ِ بَسّامٍ وَتَكْرِمَة ٍ غَرّاءَ تَعدِلُ عندي كلَّ مَوْهُوبِ", "sadr": " إلاّ بِشيمَة ِ بَسّامٍ وَتَكْرِمَة ٍ", "ajez": " غَرّاءَ تَعدِلُ عندي كلَّ مَوْهُوبِ"}, {"bayt": " انت المعين على امر تصاوله وَحَاجَة ٍ شَافَهَتْنَا بِالأعَاجيبِ", "sadr": " انت المعين على امر تصاوله", "ajez": " وَحَاجَة ٍ شَافَهَتْنَا بِالأعَاجيبِ"}, {"bayt": " وَمِثلُ سَمعِكَ يَدعُوهُ إلى كَرَمٍ قَوْلٌ تُشَيّعُهُ أنْفَاسُ مَكْرُوبِ", "sadr": " وَمِثلُ سَمعِكَ يَدعُوهُ إلى كَرَمٍ", "ajez": " قَوْلٌ تُشَيّعُهُ أنْفَاسُ مَكْرُوبِ"}, {"bayt": " سَبَى فنَاؤكَ آمَالاً لطِينَتِها سَبْيَ الأزِمّة ِ أعنَاقَ المَصَاعيبِ", "sadr": " سَبَى فنَاؤكَ آمَالاً لطِينَتِها", "ajez": " سَبْيَ الأزِمّة ِ أعنَاقَ المَصَاعيبِ"}, {"bayt": " يا خيرمن قال بلغ خير مستمع عَنّي وَحَسبُكَ مِنْ وَصْفٍ وَتَلقيبِ", "sadr": " يا خيرمن قال بلغ خير مستمع", "ajez": " عَنّي وَحَسبُكَ مِنْ وَصْفٍ وَتَلقيبِ"}, {"bayt": " لَوْلاكَ يا مَلِكَ الأمْلاكِ سَالَ بِنَا مِنَ النّوَائِبِ عَرّاصُ الشّآبِيبِ", "sadr": " لَوْلاكَ يا مَلِكَ الأمْلاكِ سَالَ بِنَا", "ajez": " مِنَ النّوَائِبِ عَرّاصُ الشّآبِيبِ"}, {"bayt": " زجرت عنا الليالي وهي رابضة تَقْرُو بِأنْيَابِهَا عَقْرَ المَخاليبِ", "sadr": " زجرت عنا الليالي وهي رابضة", "ajez": " تَقْرُو بِأنْيَابِهَا عَقْرَ المَخاليبِ"}, {"bayt": " ارعيتنا الكلأ الممطور ننشطه نشط الخمائل بعد المربع الموبي", "sadr": " ارعيتنا الكلأ الممطور ننشطه", "ajez": " نشط الخمائل بعد المربع الموبي"}, {"bayt": " فكُنتَ كالغَيثِ مَسّ المَحلَ رَيّقُهُ فَهَذّبَ الأرْضَ منهُ أيَّ تَهذِيبِ", "sadr": " فكُنتَ كالغَيثِ مَسّ المَحلَ رَيّقُهُ", "ajez": " فَهَذّبَ الأرْضَ منهُ أيَّ تَهذِيبِ"}, {"bayt": " هذا أتَى قائِلاً، وَالصّدْقُ يَنصُرُهُ اقال عنقي وكان السيف يغري بي", "sadr": " هذا أتَى قائِلاً، وَالصّدْقُ يَنصُرُهُ", "ajez": " اقال عنقي وكان السيف يغري بي"}, {"bayt": " صَدَقتَ ظَنَّ العُلَى فيه، وَحاسِدُهُ يعطي الحقائق اطراف الاكاذيب", "sadr": " صَدَقتَ ظَنَّ العُلَى فيه، وَحاسِدُهُ", "ajez": " يعطي الحقائق اطراف الاكاذيب"}, {"bayt": " تركته زاهداً في العيش منقطعاً عن القراين منا والاصاحيب", "sadr": " تركته زاهداً في العيش منقطعاً", "ajez": " عن القراين منا والاصاحيب"}, {"bayt": " وكان بالحرب يلقى من ينافره فَصَارَ يَلقَى الأعَادي بِالمَحارِيبِ", "sadr": " وكان بالحرب يلقى من ينافره", "ajez": " فَصَارَ يَلقَى الأعَادي بِالمَحارِيبِ"}, {"bayt": " ماقلت ما كان صرف الدهر ادبه بَلى قَديماً، وَهذا فَضْلُ تأدِيبِ", "sadr": " ماقلت ما كان صرف الدهر ادبه", "ajez": " بَلى قَديماً، وَهذا فَضْلُ تأدِيبِ"}, {"bayt": " الحمد لله لا أشكو الى أحد قَلّ الوَفَاءُ منَ الشبّانِ والشّيبِ", "sadr": " الحمد لله لا أشكو الى أحد", "ajez": " قَلّ الوَفَاءُ منَ الشبّانِ والشّيبِ"}, {"bayt": " هَيَّأتَ مَجدَكَ يَستَوْفي الزّمَانَ بهِ عَزْماً حُسَاماً، وَرأياً غيرَ مَغلوبِ", "sadr": " هَيَّأتَ مَجدَكَ يَستَوْفي الزّمَانَ بهِ", "ajez": " عَزْماً حُسَاماً، وَرأياً غيرَ مَغلوبِ"}, {"bayt": " ولا صبرت على ذل ومنقصة وَلا حَذِرْتَ عَلى عَذْلٍ وَتَأنِيبِ", "sadr": " ولا صبرت على ذل ومنقصة", "ajez": " وَلا حَذِرْتَ عَلى عَذْلٍ وَتَأنِيبِ"}, {"bayt": " خَطَبتَ شِعرِي إلى قَلْبٍ يَضِنّ بهِ الا عليك فباشر خير مخطوب", "sadr": " خَطَبتَ شِعرِي إلى قَلْبٍ يَضِنّ بهِ", "ajez": " الا عليك فباشر خير مخطوب"}, {"bayt": " شببت بالعز اذ كان المديح له فما اصول بمدحي دون تشبيب", "sadr": " شببت بالعز اذ كان المديح له", "ajez": " فما اصول بمدحي دون تشبيب"}, {"bayt": " لا علقَ الموت نفساً  انت صاحبها ان الحمام محب غير محبوب", "sadr": " لا علقَ الموت نفساً  انت صاحبها", "ajez": " ان الحمام محب غير محبوب"}], "era": "العصر العباسي", "title": "ما يَصْنَعُ السّيرُ بالجُرْدِ السّرَاحِيبِ"}