{"id": "19600", "author": "الأقيشر السعدي", "abyat": [{"bayt": " وَمُقْعَدِ قَوْمٍ قَدْ مَشَى مِنْ شَرَابِنَا وأَعْمَى سَقَيْنَاهُ ثَلاثاً فَأَبْصَرَا", "sadr": " وَمُقْعَدِ قَوْمٍ قَدْ مَشَى مِنْ شَرَابِنَا", "ajez": " وأَعْمَى سَقَيْنَاهُ ثَلاثاً فَأَبْصَرَا"}, {"bayt": " شَرَاباً كَرِيحِ العَنْبَرِ الوَرْدِ رِيحُهُ وَمَسْحُوقَ هِنْدِيٍّ مِنَ المِسْكِ أَذْفَرَا", "sadr": " شَرَاباً كَرِيحِ العَنْبَرِ الوَرْدِ رِيحُهُ", "ajez": " وَمَسْحُوقَ هِنْدِيٍّ مِنَ المِسْكِ أَذْفَرَا"}, {"bayt": " مِنَ الفَتَيَاتِ الغُرِّ مِنْ أرْضِ بَابِلٍ إذَا صَبَّهَا الحَانيُّ فِي الكَأْسِ كَبَّرَا", "sadr": " مِنَ الفَتَيَاتِ الغُرِّ مِنْ أرْضِ بَابِلٍ", "ajez": " إذَا صَبَّهَا الحَانيُّ فِي الكَأْسِ كَبَّرَا"}, {"bayt": " لَهَا مِنْ زُجَاجِ الشَّامِ عُنْقٌ غَرِيبَة ٌ تَأَنَّقَ فِيهَا صَانِعٌ وَتَحَيَّرَا", "sadr": " لَهَا مِنْ زُجَاجِ الشَّامِ عُنْقٌ غَرِيبَة ٌ", "ajez": " تَأَنَّقَ فِيهَا صَانِعٌ وَتَحَيَّرَا"}, {"bayt": " ذَخَائِرُ فِرْعَوْنَ التي جُبِيَتْ لَهُ وَكُلٌّ يُسَمَّى بالعَتِيقِ مُشَهَّرَا", "sadr": " ذَخَائِرُ فِرْعَوْنَ التي جُبِيَتْ لَهُ", "ajez": " وَكُلٌّ يُسَمَّى بالعَتِيقِ مُشَهَّرَا"}, {"bayt": " إذَا مَا رَآهَا بَعْدَ إنْقَاءْ غُسْلِهَا تَدُورُ عَلَيْنَا صَائِمُ القَوْمِ أفْطَرَا", "sadr": " إذَا مَا رَآهَا بَعْدَ إنْقَاءْ غُسْلِهَا", "ajez": " تَدُورُ عَلَيْنَا صَائِمُ القَوْمِ أفْطَرَا"}], "era": "العصر الإسلامي", "title": "وَمُقْعَدِ قَوْمٍ قَدْ مَشَى مِنْ شَرَابِنَا"}