{"id": "3209", "author": "الفرزدق", "abyat": [{"bayt": " أُوصي تَمِيماً إنْ قُضَاعَةَ سَاقَهَا قَوَا الغَيْثِ من دارٍ بدُومةَ أوْ جَدبِ", "sadr": " أُوصي تَمِيماً إنْ قُضَاعَةَ سَاقَهَا", "ajez": " قَوَا الغَيْثِ من دارٍ بدُومةَ أوْ جَدبِ"}, {"bayt": " إذا انتَجَعتْ كَلْبٌ عَلَيكُمْ فمكِّنوا لها الدّارَ من سَهلِ المباءةِ وَالشَّرْبِ", "sadr": " إذا انتَجَعتْ كَلْبٌ عَلَيكُمْ فمكِّنوا", "ajez": " لها الدّارَ من سَهلِ المباءةِ وَالشَّرْبِ"}, {"bayt": " فإنّهُمُ الأحْلافُ، والغَيْثُ، مَرّةً، يَكُونُ بشَرْقٍ من بلادٍ وَمن غَرْبِ", "sadr": " فإنّهُمُ الأحْلافُ، والغَيْثُ، مَرّةً،", "ajez": " يَكُونُ بشَرْقٍ من بلادٍ وَمن غَرْبِ"}, {"bayt": " أشَدُّ حِبَالٍ بَينَ حَيّينِ، مِرّةً، حِبَالٌ أُمِرّتْ من تميمٍ وَمن كَلبِ", "sadr": " أشَدُّ حِبَالٍ بَينَ حَيّينِ، مِرّةً،", "ajez": " حِبَالٌ أُمِرّتْ من تميمٍ وَمن كَلبِ"}, {"bayt": " وَلَيْسَ قُضَاعيٌّ لَدَيْنَا بخَائِفٍ، وَإنْ أصْبحتْ تَغلي القدورُ من الحرْبِ", "sadr": " وَلَيْسَ قُضَاعيٌّ لَدَيْنَا بخَائِفٍ،", "ajez": " وَإنْ أصْبحتْ تَغلي القدورُ من الحرْبِ"}, {"bayt": " فَإنّ تَمِيماً لا يُجِيرُ عَلَيْهِمُ عَزِيزٌ وَلا صِنْديدُ مَملكَةٍ غُلْبِ", "sadr": " فَإنّ تَمِيماً لا يُجِيرُ عَلَيْهِمُ", "ajez": " عَزِيزٌ وَلا صِنْديدُ مَملكَةٍ غُلْبِ"}, {"bayt": " هُمُ المُتَخَلّى أنْ يُجَارَ عَلَيْهمُ إذا استَعَرَتْ عدوَى المعبَّدة الجُرْبِ", "sadr": " هُمُ المُتَخَلّى أنْ يُجَارَ عَلَيْهمُ", "ajez": " إذا استَعَرَتْ عدوَى المعبَّدة الجُرْبِ"}, {"bayt": " وَأجْسَمُ مِنْ عادٍ جُسُومُ رِجالِهمْ، وأَكثرُ إنْ عُدّوا عديداً مِنَ التُّرْبِ", "sadr": " وَأجْسَمُ مِنْ عادٍ جُسُومُ رِجالِهمْ،", "ajez": " وأَكثرُ إنْ عُدّوا عديداً مِنَ التُّرْبِ"}, {"bayt": " مَصَاليتُ عِندَ الرّوْعِ في كلّ مَوْطِنٍ إذا شخصَتْ نَفسُ الجبان من الرّعبِ", "sadr": " مَصَاليتُ عِندَ الرّوْعِ في كلّ مَوْطِنٍ", "ajez": " إذا شخصَتْ نَفسُ الجبان من الرّعبِ"}], "era": "العصر الإسلامي", "title": "أوصي تميما إن قضاعة ساقها"}