{"id": "69521", "author": "الأسود بن يعفر النهشلي", "abyat": [{"bayt": " أجَدَّ الشبابُ قد مَضى فَتَسرَّعا    وبانَ كَما بانَ الخليطُ فوَدَّعا\r", "sadr": " أجَدَّ الشبابُ قد مَضى فَتَسرَّعا", "ajez": "    وبانَ كَما بانَ الخليطُ فوَدَّعا\r"}, {"bayt": " وما كان مذموماً لدينا ثناؤه     وصُحبَتُهُ ما لفَّنا خُلُطٌ معا\r", "sadr": " وما كان مذموماً لدينا ثناؤه", "ajez": "     وصُحبَتُهُ ما لفَّنا خُلُطٌ معا\r"}, {"bayt": " فبانَ وجَلّ الشيبُ في رسم دارهِ     كما خفَّ فَرخٌ ناهِض فَتَرفعا\r", "sadr": " فبانَ وجَلّ الشيبُ في رسم دارهِ", "ajez": "     كما خفَّ فَرخٌ ناهِض فَتَرفعا\r"}, {"bayt": " فأصبح أخداني كأنّ عليهم      ملاءَ العراق والثغام المنزَّعا\r", "sadr": " فأصبح أخداني كأنّ عليهم", "ajez": "      ملاءَ العراق والثغام المنزَّعا\r"}, {"bayt": " يُبينُهمُ ذو اللبّ حينَ يراهُمُ     بسيماهُمُ بِيضاً لحاهُم وأصلعا", "sadr": " يُبينُهمُ ذو اللبّ حينَ يراهُمُ", "ajez": "     بسيماهُمُ بِيضاً لحاهُم وأصلعا"}], "era": "العصر الجاهلي", "title": "أجَدَّ الشبابُ قد مَضى فَتَسرَّعا"}