{"id": "17431", "author": "الأخطل", "abyat": [{"bayt": " عفا واسطٌ من أهْله فمذانُبْهْ فرَوْضُ القَطا: صَحْراؤهُ فَنصائِبُهْ", "sadr": " عفا واسطٌ من أهْله فمذانُبْهْ", "ajez": " فرَوْضُ القَطا: صَحْراؤهُ فَنصائِبُهْ"}, {"bayt": " وقدْ كانَ محضُوراً أرى أن أهلهُ به أبداً، ما أعجمَ الخطَّ كاتبُهْ", "sadr": " وقدْ كانَ محضُوراً أرى أن أهلهُ", "ajez": " به أبداً، ما أعجمَ الخطَّ كاتبُهْ"}, {"bayt": " ولكنَّ هذا الدهرَ أصبحَ فانياً تَسَعْسعَ واشْتَدَّتْ عَلينا تجارِبُهْ", "sadr": " ولكنَّ هذا الدهرَ أصبحَ فانياً", "ajez": " تَسَعْسعَ واشْتَدَّتْ عَلينا تجارِبُهْ"}, {"bayt": " عَدا ذو الصَّفا منْهُمْ، فأمسى أنيسُهُ قليلاً، تعاوى بالضباحِ ثعالبُهْ", "sadr": " عَدا ذو الصَّفا منْهُمْ، فأمسى أنيسُهُ", "ajez": " قليلاً، تعاوى بالضباحِ ثعالبُهْ"}, {"bayt": " وحلَّ بصحراء الإهالة ِ حذلمٌ وما كانَ حلالاً بها، إذا نُحاربُهْ", "sadr": " وحلَّ بصحراء الإهالة ِ حذلمٌ", "ajez": " وما كانَ حلالاً بها، إذا نُحاربُهْ"}, {"bayt": " خلا لبني البرشاء بكرِ بن وائلٍ مجاري الحصى من بطنِ فلجٍ، فجانبُهْ", "sadr": " خلا لبني البرشاء بكرِ بن وائلٍ", "ajez": " مجاري الحصى من بطنِ فلجٍ، فجانبُهْ"}, {"bayt": " نَفى عَنْهُمُ الأعْداءَ فُرْسانُ غارَة ٍ ودهمٌ يغمُ البلقَ خضرٌ كتائبهُ", "sadr": " نَفى عَنْهُمُ الأعْداءَ فُرْسانُ غارَة ٍ", "ajez": " ودهمٌ يغمُ البلقَ خضرٌ كتائبهُ"}, {"bayt": " فنحنُ أخٌ، لم يلقَ في الناسِ مثلُنا أخاً، حين شابَ الدهرُ وابيضّ حاجبهْ", "sadr": " فنحنُ أخٌ، لم يلقَ في الناسِ مثلُنا", "ajez": " أخاً، حين شابَ الدهرُ وابيضّ حاجبهْ"}, {"bayt": " وإنا لصبرٌ في مواطنِ قومِنا إذا ما القَنا الخَطِّيُّ عُلّتْ مخاضِبُهْ", "sadr": " وإنا لصبرٌ في مواطنِ قومِنا", "ajez": " إذا ما القَنا الخَطِّيُّ عُلّتْ مخاضِبُهْ"}, {"bayt": " وإنا لحمّالو العدو، إذا عدا عَلى مَرْكبٍ، لا تُسْتَلَذُّ مَراكِبُهْ", "sadr": " وإنا لحمّالو العدو، إذا عدا", "ajez": " عَلى مَرْكبٍ، لا تُسْتَلَذُّ مَراكِبُهْ"}, {"bayt": " وغيرانَ يغلي للعدواة ِ صدرهُ تذبذبَ عني، لم تنلني مخالبهُ", "sadr": " وغيرانَ يغلي للعدواة ِ صدرهُ", "ajez": " تذبذبَ عني، لم تنلني مخالبهُ"}, {"bayt": " فإنْ أكُ قد فتّ الكليبي بالعلى فقدْ أهلكتهُ في الجراء مثالِبُه", "sadr": " فإنْ أكُ قد فتّ الكليبي بالعلى", "ajez": " فقدْ أهلكتهُ في الجراء مثالِبُه"}, {"bayt": " وظلَّ لهُ بينَ العُقابِ وراهطٍ ضَبابة ُ يَوْمٍ، لا تَوارى كواكِبَهْ", "sadr": " وظلَّ لهُ بينَ العُقابِ وراهطٍ", "ajez": " ضَبابة ُ يَوْمٍ، لا تَوارى كواكِبَهْ"}, {"bayt": " رأيتكَ، والتكليفَ نفسكَ دارماً كشيءٍ مضى ، لا يُدركُ الدهرَ طالبهْ", "sadr": " رأيتكَ، والتكليفَ نفسكَ دارماً", "ajez": " كشيءٍ مضى ، لا يُدركُ الدهرَ طالبهْ"}, {"bayt": " فإنْ يكُ قَدْ بانَ الشّبابُ، فرُبّما أعلّلُ بالعذبِ اللذيذِ مشاربُهْ", "sadr": " فإنْ يكُ قَدْ بانَ الشّبابُ، فرُبّما", "ajez": " أعلّلُ بالعذبِ اللذيذِ مشاربُهْ"}, {"bayt": " ولَيْلَة ِ نَجْوى يعْتري أهْلَها الصّبى سَلَبْتُ بها ريماً، جميلاً مَسالبُهْ", "sadr": " ولَيْلَة ِ نَجْوى يعْتري أهْلَها الصّبى", "ajez": " سَلَبْتُ بها ريماً، جميلاً مَسالبُهْ"}, {"bayt": " فأصبحَ محجوباً عليَّ، وأصبحتْ بظاهرة ٍ آثارهُ وملاعبهْ", "sadr": " فأصبحَ محجوباً عليَّ، وأصبحتْ", "ajez": " بظاهرة ٍ آثارهُ وملاعبهْ"}, {"bayt": " وبتنا كأنّا ضيفُ جنّ بليلة ٍ يعودُ بها القَلْبَ السّقيمَ صبائِبُهْ", "sadr": " وبتنا كأنّا ضيفُ جنّ بليلة ٍ", "ajez": " يعودُ بها القَلْبَ السّقيمَ صبائِبُهْ"}, {"bayt": " فيا لك مني هفوة ً، لم أعُدْ لها ويا لكَ قلباً، أهلكتُه مذاهبهْ", "sadr": " فيا لك مني هفوة ً، لم أعُدْ لها", "ajez": " ويا لكَ قلباً، أهلكتُه مذاهبهْ"}, {"bayt": " دعاني إلى خير الملوكِ فضولهُ وأنّي امْرؤ مُثْنٍ عَلَيْهِ ونادِبُهْ", "sadr": " دعاني إلى خير الملوكِ فضولهُ", "ajez": " وأنّي امْرؤ مُثْنٍ عَلَيْهِ ونادِبُهْ"}, {"bayt": " وعالق أسبابِ امريٍ، إن أقع به أقع بكريمٍ، لا تغبّ مواهبُهْ", "sadr": " وعالق أسبابِ امريٍ، إن أقع به", "ajez": " أقع بكريمٍ، لا تغبّ مواهبُهْ"}, {"bayt": " إلى فاعلٍ لوْ خايَلَ النِّيلَ، أزْحفَتْ من النيلِ فوراتُهْو مثاعِبُهْ", "sadr": " إلى فاعلٍ لوْ خايَلَ النِّيلَ، أزْحفَتْ", "ajez": " من النيلِ فوراتُهْو مثاعِبُهْ"}, {"bayt": " وإنْ أتَعَرَّضْ للوليدِ، فإنّهُ نَمَتْهُ إلى خيرِ الفُروعِ مَضاربُهْ", "sadr": " وإنْ أتَعَرَّضْ للوليدِ، فإنّهُ", "ajez": " نَمَتْهُ إلى خيرِ الفُروعِ مَضاربُهْ"}, {"bayt": " نساءُ بني عَبْسٍ وكَعْبٍ ولَدْنَهُ فنِعْمَ، لعَمْري، الحالباتُ حوالبُهْ", "sadr": " نساءُ بني عَبْسٍ وكَعْبٍ ولَدْنَهُ", "ajez": " فنِعْمَ، لعَمْري، الحالباتُ حوالبُهْ"}, {"bayt": " رفيع المنى ، لا يستقلُّ بهمهِ سؤومٌ، ولا مستنكشُ البحرُ ناضبِهْ", "sadr": " رفيع المنى ، لا يستقلُّ بهمهِ", "ajez": " سؤومٌ، ولا مستنكشُ البحرُ ناضبِهْ"}, {"bayt": " تجيشُ بأوصالِ الجزورِ قدورهُ إذا المحلُ لم يرجعْ بعودينِ حاطبهْ", "sadr": " تجيشُ بأوصالِ الجزورِ قدورهُ", "ajez": " إذا المحلُ لم يرجعْ بعودينِ حاطبهْ"}, {"bayt": " مطاعيمُ تغدو بالعبيطِ جِفانهُم إذا القُرُّ ألوَتْ بالعِضاهِ عَصائِبُهْ", "sadr": " مطاعيمُ تغدو بالعبيطِ جِفانهُم", "ajez": " إذا القُرُّ ألوَتْ بالعِضاهِ عَصائِبُهْ"}, {"bayt": " تضيءُ لنا الظلماءَ غرة ُ وجههِ إذا الأقعسُ المبطانُ أُرْتِجَ حاجِبُهْ", "sadr": " تضيءُ لنا الظلماءَ غرة ُ وجههِ", "ajez": " إذا الأقعسُ المبطانُ أُرْتِجَ حاجِبُهْ"}, {"bayt": " وما بلَغَتْ خَيْلُ امرىء ٍ كانَ قَبْلَهُ بحيثُ انتهتْ آثارُهُ ومحاربهْ", "sadr": " وما بلَغَتْ خَيْلُ امرىء ٍ كانَ قَبْلَهُ", "ajez": " بحيثُ انتهتْ آثارُهُ ومحاربهْ"}, {"bayt": " وتُضْحي جبالُ الروم غُبراً فِجاجُها بما اشعلتْ غاراتُهُ ومقانبهْ", "sadr": " وتُضْحي جبالُ الروم غُبراً فِجاجُها", "ajez": " بما اشعلتْ غاراتُهُ ومقانبهْ"}, {"bayt": " مِن الغَزْوِ، حتى انْضَمَّ كلُّ ثميلة ٍ وحتى انطوَتْ مِن طولِ قَوْدٍ جنائبُهْ", "sadr": " مِن الغَزْوِ، حتى انْضَمَّ كلُّ ثميلة ٍ", "ajez": " وحتى انطوَتْ مِن طولِ قَوْدٍ جنائبُهْ"}, {"bayt": " يمدُّ المدى للقومِ، حتى تقطعتْ حبالُ القُوى ، وانشَقَّ مِنْهُ سَبائبُهْ", "sadr": " يمدُّ المدى للقومِ، حتى تقطعتْ", "ajez": " حبالُ القُوى ، وانشَقَّ مِنْهُ سَبائبُهْ"}, {"bayt": " فتى النّاسِ لمْ تُصْهِرْ إليهِ مُحارِبٌ ولا غنوي دون قيسٍ يُناسبهُ", "sadr": " فتى النّاسِ لمْ تُصْهِرْ إليهِ مُحارِبٌ", "ajez": " ولا غنوي دون قيسٍ يُناسبهُ"}], "era": "العصر الإسلامي", "title": "عفا واسطٌ من أهْله فمذانُبْهْ"}