{"id": "26352", "author": "معاوية بن أبي سفيان", "abyat": [{"bayt": " إذا أنا أعطيتُ القليلَ شكوتُمُ وإنْ أنا أعطيتُ الكثيرَ فَلا شكْرُ", "sadr": " إذا أنا أعطيتُ القليلَ شكوتُمُ", "ajez": " وإنْ أنا أعطيتُ الكثيرَ فَلا شكْرُ"}, {"bayt": " ومَا لمْتُ نَفْسي في قضَاءِ حقوقكمْ وقَد كانَ لي فيما اعتذرتُ به عُذْرُ", "sadr": " ومَا لمْتُ نَفْسي في قضَاءِ حقوقكمْ", "ajez": " وقَد كانَ لي فيما اعتذرتُ به عُذْرُ"}, {"bayt": " وأَمْنَحُكُمْ مالي، وتُكْفَرُ نِعْمَتِي وتَشتُمُ عِرْضي في مجالسها فِهْرُ", "sadr": " وأَمْنَحُكُمْ مالي، وتُكْفَرُ نِعْمَتِي", "ajez": " وتَشتُمُ عِرْضي في مجالسها فِهْرُ"}, {"bayt": " إذا العذرُ لم يُقبَلْ ، ولم يَنفعِ الأسَى وضَاقتْ قلوبٌ منهُمُ حَشْوُها الغِمْرُ", "sadr": " إذا العذرُ لم يُقبَلْ ، ولم يَنفعِ الأسَى", "ajez": " وضَاقتْ قلوبٌ منهُمُ حَشْوُها الغِمْرُ"}, {"bayt": " فكيفَ أداوِي داءكُمْ ، ودواؤُكمْ يزيدكُم غيّاً ؟ ! فقد عظُمُ الأمْرُ", "sadr": " فكيفَ أداوِي داءكُمْ ، ودواؤُكمْ", "ajez": " يزيدكُم غيّاً ؟ ! فقد عظُمُ الأمْرُ"}, {"bayt": " سَأَحْرِمُكُمْ حَتّى يَذِلّ صِعَابُكمْ وأبلَغُ شَى ْءٍ في صلاحكُمُ الفَقْرُ", "sadr": " سَأَحْرِمُكُمْ حَتّى يَذِلّ صِعَابُكمْ", "ajez": " وأبلَغُ شَى ْءٍ في صلاحكُمُ الفَقْرُ"}], "era": "العصر الإسلامي", "title": "إذا أنا أعطيتُ القليلَ شكوتُمُ"}