{"id": "24211", "author": "عبد الله الخفاجي", "abyat": [{"bayt": " إلَيْكَ عَنِّي فَلَيْسَ الخَوْفُ مِنْ شِيَمِي سَيَطْرُدُ الهَمَّ مَا يَسْمُو مِنَ الهِمَمِ", "sadr": " إلَيْكَ عَنِّي فَلَيْسَ الخَوْفُ مِنْ شِيَمِي", "ajez": " سَيَطْرُدُ الهَمَّ مَا يَسْمُو مِنَ الهِمَمِ"}, {"bayt": " إذَا سُرِرْتُ فَمَا ثَغْرِي بِمُبْتَسِم وَإنْ جَزِعْتُ فَمَا دَمْعِي بِمُنْسَجِمِ", "sadr": " إذَا سُرِرْتُ فَمَا ثَغْرِي بِمُبْتَسِم", "ajez": " وَإنْ جَزِعْتُ فَمَا دَمْعِي بِمُنْسَجِمِ"}, {"bayt": " يَا نَاشِدَ العِزِّ مَطْوِيَّا عَلَى ضَمَدٍ ما يدركُ المجدُ بينَ الشاءِ والنعمِ", "sadr": " يَا نَاشِدَ العِزِّ مَطْوِيَّا عَلَى ضَمَدٍ", "ajez": " ما يدركُ المجدُ بينَ الشاءِ والنعمِ"}, {"bayt": " أمَامَكَ القَاعُ فَاقْذِفْهَا مُضْمَرَة ً كأنمَا وضحتْ أخفافهَا بدمِ", "sadr": " أمَامَكَ القَاعُ فَاقْذِفْهَا مُضْمَرَة ً", "ajez": " كأنمَا وضحتْ أخفافهَا بدمِ"}, {"bayt": " حتَّى تراهَا وقدْ أودَى الكلالُ بهَا وفي مناسمهَا عقلٌ منَ الخدمِ", "sadr": " حتَّى تراهَا وقدْ أودَى الكلالُ بهَا", "ajez": " وفي مناسمهَا عقلٌ منَ الخدمِ"}, {"bayt": " وصاحبٍ كغرارِ العضبِ مفترشٍ نمارقَ الرملِ طلاع علَى الظلمِ", "sadr": " وصاحبٍ كغرارِ العضبِ مفترشٍ", "ajez": " نمارقَ الرملِ طلاع علَى الظلمِ"}, {"bayt": " يخالسُ الصبح والظلماء تحجبهُ تَسَتُّرَ البَرْقِ بَيْنَ الوَابِلِ الرَّدِمِ", "sadr": " يخالسُ الصبح والظلماء تحجبهُ", "ajez": " تَسَتُّرَ البَرْقِ بَيْنَ الوَابِلِ الرَّدِمِ"}, {"bayt": " يهبُّ يعثرُ في أذيالهِ وسناً كأنمَا النومُ بينَ الساقِ والقدمِ", "sadr": " يهبُّ يعثرُ في أذيالهِ وسناً", "ajez": " كأنمَا النومُ بينَ الساقِ والقدمِ"}, {"bayt": " هلمَّ نرسلهَا هوجاء سامية ً لا يَمْنَعُ السَّيْفُ فِيْهَا خُدْعَة َ القَلَمِ", "sadr": " هلمَّ نرسلهَا هوجاء سامية ً", "ajez": " لا يَمْنَعُ السَّيْفُ فِيْهَا خُدْعَة َ القَلَمِ"}, {"bayt": " إنَّا إذَا الحَيُّ لا تَرْعَى سَوَائِمُهُ إلاَّ تَذَكُّرَ رِيْحِ الضَالِ وَالسِّلَمِ", "sadr": " إنَّا إذَا الحَيُّ لا تَرْعَى سَوَائِمُهُ", "ajez": " إلاَّ تَذَكُّرَ رِيْحِ الضَالِ وَالسِّلَمِ"}, {"bayt": " وَأخْمَدَ البَرْقَ حَتَّى فِي بُيُوتِهِمُ مَا يُظْهِرُ الزَنْدُ مَا فِيْهِ مِنَ الضَّرَّمِ", "sadr": " وَأخْمَدَ البَرْقَ حَتَّى فِي بُيُوتِهِمُ", "ajez": " مَا يُظْهِرُ الزَنْدُ مَا فِيْهِ مِنَ الضَّرَّمِ"}, {"bayt": " وَرَاحَتْ النِّيْبُ فِي الأنْسَاعِ سَاغِبَة ً تنافسُ الخيلَ إنْ عللنَ باللجمِ", "sadr": " وَرَاحَتْ النِّيْبُ فِي الأنْسَاعِ سَاغِبَة ً", "ajez": " تنافسُ الخيلَ إنْ عللنَ باللجمِ"}, {"bayt": " نبنَا عنِ الغيثِ أحياناً فحلتنَا لا يَعْدَمُ الغَيْثُ فِيْهَا هَاطِلَ الدِّيَمِ", "sadr": " نبنَا عنِ الغيثِ أحياناً فحلتنَا", "ajez": " لا يَعْدَمُ الغَيْثُ فِيْهَا هَاطِلَ الدِّيَمِ"}, {"bayt": " هلمَّ طيفَ سليمَى قدْ جلوتَ لنَا غياهبَ الصدِّ لولا خدعة ُ الحلمِ", "sadr": " هلمَّ طيفَ سليمَى قدْ جلوتَ لنَا", "ajez": " غياهبَ الصدِّ لولا خدعة ُ الحلمِ"}, {"bayt": " نَشَدْتُكَ الله هَلْ أنْسِيتَ لَيْلَتَنَا عَلَى الثَّنِيَّة ِ دُونَ السَّفْحِ مِنْ إضَمِ", "sadr": " نَشَدْتُكَ الله هَلْ أنْسِيتَ لَيْلَتَنَا", "ajez": " عَلَى الثَّنِيَّة ِ دُونَ السَّفْحِ مِنْ إضَمِ"}, {"bayt": " وليلة الحي إذْ أغرَى الرقيبُ بنَا فَمَا اتَّقَيْنَا بِغَيْرِ الخُمْرِ وَاللثمِ", "sadr": " وليلة الحي إذْ أغرَى الرقيبُ بنَا", "ajez": " فَمَا اتَّقَيْنَا بِغَيْرِ الخُمْرِ وَاللثمِ"}, {"bayt": " فَكَيْفَ تَقْذِفُ وُدَّاً كُنْتَ تَحْفَظُهُ لَقَدْ خَصَمْتُكَ لَو صِرْنَا إلَى حَكَمِ", "sadr": " فَكَيْفَ تَقْذِفُ وُدَّاً كُنْتَ تَحْفَظُهُ", "ajez": " لَقَدْ خَصَمْتُكَ لَو صِرْنَا إلَى حَكَمِ"}, {"bayt": " لَولا عَقَابِيْلُ وَجْدِي قُلْتُ حُبُّهُم كخلبِ البرقِ لمْ يمطرْ ولمْ يدمِ", "sadr": " لَولا عَقَابِيْلُ وَجْدِي قُلْتُ حُبُّهُم", "ajez": " كخلبِ البرقِ لمْ يمطرْ ولمْ يدمِ"}, {"bayt": " وبانة ُ السفحِ تغريني بذكرهمُ وجداً فيا ليتهَا باتتْ كعهدهمِ", "sadr": " وبانة ُ السفحِ تغريني بذكرهمُ", "ajez": " وجداً فيا ليتهَا باتتْ كعهدهمِ"}, {"bayt": " هل الأجيرعُ يشفي منْ يمرُّ بهِ بالعرفِ أمْ ذاكَ معْ أيامنَا القدمِ", "sadr": " هل الأجيرعُ يشفي منْ يمرُّ بهِ", "ajez": " بالعرفِ أمْ ذاكَ معْ أيامنَا القدمِ"}, {"bayt": " وَنَشْقَة خَطَرَتْ وَالرَّكْبُ مُشْتَمِلٌ ذُؤابَهَ اللَّيْلِ بَيْنَ الأيْنُقِ الرُّسُمِ", "sadr": " وَنَشْقَة خَطَرَتْ وَالرَّكْبُ مُشْتَمِلٌ", "ajez": " ذُؤابَهَ اللَّيْلِ بَيْنَ الأيْنُقِ الرُّسُمِ"}, {"bayt": " شاقتْ طلى حانها وافى رحالهم سُكْراً مِنَ السَّيْرِ أوْ ضُعْفَاً مِنَ السَّقْمِ", "sadr": " شاقتْ طلى حانها وافى رحالهم", "ajez": " سُكْراً مِنَ السَّيْرِ أوْ ضُعْفَاً مِنَ السَّقْمِ"}, {"bayt": " آهاً لِقَلْبِكَ مِنْ نَجْدٍ وَسَاكِنهِ لقدْ علقتَ بشعبٍ غيرِ ملتئمِ", "sadr": " آهاً لِقَلْبِكَ مِنْ نَجْدٍ وَسَاكِنهِ", "ajez": " لقدْ علقتَ بشعبٍ غيرِ ملتئمِ"}, {"bayt": " ما هبتِ الريحُ إلاَّ منْ جوانبهِ ولاَ علا الشيحُ إلاَّ ذروة َ العلمِ", "sadr": " ما هبتِ الريحُ إلاَّ منْ جوانبهِ", "ajez": " ولاَ علا الشيحُ إلاَّ ذروة َ العلمِ"}, {"bayt": " للهِ ليلكَ كمْ أفنيتَ منْ جلدٍ حَتَّى الصَّبَاح وَكَمْ أبْقَيْتُ مِنْ ألَمِ", "sadr": " للهِ ليلكَ كمْ أفنيتَ منْ جلدٍ", "ajez": " حَتَّى الصَّبَاح وَكَمْ أبْقَيْتُ مِنْ ألَمِ"}], "era": "العصر العباسي", "title": "إلَيْكَ عَنِّي فَلَيْسَ الخَوْفُ مِنْ شِيَمِي"}