{"id": "25636", "author": "أبو نواس", "abyat": [{"bayt": " وشادِنٍ تَسْحَرُ عَيناهُ، أسْـفـلَـهُ يَـجـذِبُ  أعْــلاهُ", "sadr": " وشادِنٍ تَسْحَرُ عَيناهُ،", "ajez": " أسْـفـلَـهُ يَـجـذِبُ  أعْــلاهُ"}, {"bayt": " يَنظُرُ مَوْلاهُ إلى وَجهِهِ، يا لَيتَني عَينٌ لِمَوْلاهُ", "sadr": " يَنظُرُ مَوْلاهُ إلى وَجهِهِ،", "ajez": " يا لَيتَني عَينٌ لِمَوْلاهُ"}, {"bayt": " أعَرْتُهُ رُوحي وقَلبي؛ فقد عَيِيتُ مِمّا أتَقاضاهُ", "sadr": " أعَرْتُهُ رُوحي وقَلبي؛ فقد", "ajez": " عَيِيتُ مِمّا أتَقاضاهُ"}, {"bayt": " ولَوْ رآني سَيّئاً في الهوَى ، لَقَالَ لي: أبْعَدَكَ الله!", "sadr": " ولَوْ رآني سَيّئاً في الهوَى ،", "ajez": " لَقَالَ لي: أبْعَدَكَ الله!"}], "era": "العصر العباسي", "title": "وشادِنٍ تَسْحَرُ عَيناهُ،"}