{"id": "27370", "author": "الخالديان", "abyat": [{"bayt": " كَأَنِّي بِهِمْ إِذْ خَالَفُوا بَعْضِ أَمْرِهِ وقدْ جُمِعَتْ أعناقُهُمْ والسَّلاسِلُ", "sadr": " كَأَنِّي بِهِمْ إِذْ خَالَفُوا بَعْضِ أَمْرِهِ", "ajez": " وقدْ جُمِعَتْ أعناقُهُمْ والسَّلاسِلُ"}, {"bayt": " وَصِيغَتْ خَلاخِيلٌ لَهُمْ وأَساورٌ عَلَى أَنَّ حَاليها مَدَى الدَّهْر عَاطِل", "sadr": " وَصِيغَتْ خَلاخِيلٌ لَهُمْ وأَساورٌ", "ajez": " عَلَى أَنَّ حَاليها مَدَى الدَّهْر عَاطِل"}, {"bayt": " فلا نُزِعَتْ تِلْكَ الأساوِرُ عنهُمُ ولا فَارَقْتْهُمْ في الحَياة ِ الخَلاخِلُ", "sadr": " فلا نُزِعَتْ تِلْكَ الأساوِرُ عنهُمُ", "ajez": " ولا فَارَقْتْهُمْ في الحَياة ِ الخَلاخِلُ"}], "era": "العصر العباسي", "title": "كَأَنِّي بِهِمْ إِذْ خَالَفُوا بَعْضِ أَمْرِهِ"}