{"id": "2776", "author": "البحتري", "abyat": [{"bayt": " إِن تأَملْ مَحاسِنَ الأَصبَهَاني تجدْ طَولهُ أَخا طُولِ بَاعِهْ", "sadr": " إِن تأَملْ مَحاسِنَ الأَصبَهَاني", "ajez": " تجدْ طَولهُ أَخا طُولِ بَاعِهْ"}, {"bayt": " أَو تُحصِّلْهُ لاَ تُحصِّل خِلافا بَيْنَ مَراهُ بَادِياً وسَماعِهْ", "sadr": " أَو تُحصِّلْهُ لاَ تُحصِّل خِلافا", "ajez": " بَيْنَ مَراهُ بَادِياً وسَماعِهْ"}, {"bayt": " يُؤْخدُ الْحلمُ من مَكيثِ تَأَنِّيهِ ونُجْحُ العِداتِ من إِسراعِهْ", "sadr": " يُؤْخدُ الْحلمُ من مَكيثِ تَأَنِّيهِ", "ajez": " ونُجْحُ العِداتِ من إِسراعِهْ"}, {"bayt": " يَنزِلُ القَومُ أَنفُساً وسَجايا عن تَعَلَّيهِ فوْقَهُمْ وارْتِفاعِهْ", "sadr": " يَنزِلُ القَومُ أَنفُساً وسَجايا", "ajez": " عن تَعَلَّيهِ فوْقَهُمْ وارْتِفاعِهْ"}, {"bayt": " مُنْصبٌ نفسهُ لِمكتَسبِالحَمْد يُرى أَنهُ مَكانُ ابتِداعِهْ", "sadr": " مُنْصبٌ نفسهُ لِمكتَسبِالحَمْد", "ajez": " يُرى أَنهُ مَكانُ ابتِداعِهْ"}, {"bayt": " يا أبا عبدِ اللهِ عَمَّرَكَ الَّلهُ ،لِعُرفٍ عَمَمتنا باصْطِناعِهْ", "sadr": " يا أبا عبدِ اللهِ عَمَّرَكَ الَّلهُ", "ajez": " ،لِعُرفٍ عَمَمتنا باصْطِناعِهْ"}, {"bayt": " أَكْثرُ النَّيلِ ضائِعٌ غير ما يَسْري إِلي نابهِ الثَّناءِ مُذاعِهْ", "sadr": " أَكْثرُ النَّيلِ ضائِعٌ غير ما", "ajez": " يَسْري إِلي نابهِ الثَّناءِ مُذاعِهْ"}, {"bayt": " لاَ تلُمني إِن ضِقتُ دون قَوَافي الشِّعرِ أَو كِلتُ للصَّديق بِضاعِهْ", "sadr": " لاَ تلُمني إِن ضِقتُ دون قَوَافي الشِّعرِ", "ajez": " أَو كِلتُ للصَّديق بِضاعِهْ"}, {"bayt": " ولضَنَّي بالشِّعّر أَعذَبُ ِمن ضنَّ وَجيهٍ بِكُتْبهِ ورِقاعِه", "sadr": " ولضَنَّي بالشِّعّر أَعذَبُ ِمن ضنَّ", "ajez": " وَجيهٍ بِكُتْبهِ ورِقاعِه"}, {"bayt": " إِن هذا القَريضَ نبتٌ من القوْلِ يزِيدُ الفعَالُ في إِينَاعِهْ", "sadr": " إِن هذا القَريضَ نبتٌ من القوْلِ", "ajez": " يزِيدُ الفعَالُ في إِينَاعِهْ"}, {"bayt": " هُو عِلقٌ تاجَرتني فيه بالْحيلَةِ حتَّى غَبَنْتَنِي بابْتِياعِهْ", "sadr": " هُو عِلقٌ تاجَرتني فيه", "ajez": " بالْحيلَةِ حتَّى غَبَنْتَنِي بابْتِياعِهْ"}], "era": "العصر العباسي", "title": "إن تأمل محاسن الأصبهاني"}