{"id": "11968", "author": "أبو العتاهية", "abyat": [{"bayt": " دعنيَ منْ ذكرِ أبٍ وجدِّ ونَسَبٍ يُعليكَ سُورَ المَجْدِ", "sadr": " دعنيَ منْ ذكرِ أبٍ وجدِّ", "ajez": " ونَسَبٍ يُعليكَ سُورَ المَجْدِ"}, {"bayt": " ما الفَخرُ إلاّ في التّقَى والزّهْدِ، وطاعة ٍ تعطِي جِنانَ الخُلْدِ", "sadr": " ما الفَخرُ إلاّ في التّقَى والزّهْدِ،", "ajez": " وطاعة ٍ تعطِي جِنانَ الخُلْدِ"}, {"bayt": " لا بُدَّ منْ وردٍ لأهْلِ الورْدِ إمّا إلى خَجَلٍ، وإمّا عَدّ", "sadr": " لا بُدَّ منْ وردٍ لأهْلِ الورْدِ", "ajez": " إمّا إلى خَجَلٍ، وإمّا عَدّ"}], "era": "العصر العباسي", "title": "دعنيَ منْ ذكرِ أبٍ وجدِّ"}