{"id": "25626", "author": "أبو نواس", "abyat": [{"bayt": " مُتَتايِهٌ بِجَمالِهِ صَلِفٌ، لا يُستطاعُ كلامهُ تيها", "sadr": " مُتَتايِهٌ بِجَمالِهِ صَلِفٌ،", "ajez": " لا يُستطاعُ كلامهُ تيها"}, {"bayt": " للحُسْنِ في وَجَناتِهِ بِدَعٌ، ما إنْ يَمَلّ الدّرْسَ قاريها", "sadr": " للحُسْنِ في وَجَناتِهِ بِدَعٌ،", "ajez": " ما إنْ يَمَلّ الدّرْسَ قاريها"}, {"bayt": " لوْ كانَتِ الأشياءُ تَعْقِلُهُ، أجللْنَهُ إجلالَ باريها", "sadr": " لوْ كانَتِ الأشياءُ تَعْقِلُهُ،", "ajez": " أجللْنَهُ إجلالَ باريها"}, {"bayt": " لوْ تَستَطيعُ الأرْضُ لانقَبَضَتْ حتى يَصِيرَ جَميعُهُ فيهَا", "sadr": " لوْ تَستَطيعُ الأرْضُ لانقَبَضَتْ", "ajez": " حتى يَصِيرَ جَميعُهُ فيهَا"}], "era": "العصر العباسي", "title": "مُتَتايِهٌ بِجَمالِهِ صَلِفٌ،"}