{"id": "27453", "author": "ابن حيوس", "abyat": [{"bayt": " كُنْ بَعِيداً إِنْ شِئْتَ أَوْ كُنْ قَرِيبا فَأَيادِيكَ عِنْدَنا لَنْ تَغِيبا", "sadr": " كُنْ بَعِيداً إِنْ شِئْتَ أَوْ كُنْ قَرِيبا", "ajez": " فَأَيادِيكَ عِنْدَنا لَنْ تَغِيبا"}, {"bayt": " خَلَفَتْكَ الآلاَءُ مُذْ سِرْتَ فِينا فتساويتَ مشهداً وَمغيبا", "sadr": " خَلَفَتْكَ الآلاَءُ مُذْ سِرْتَ فِينا", "ajez": " فتساويتَ مشهداً وَمغيبا"}, {"bayt": " كَالغَمَامِ الرُّكامِ يَمْضِي وَيُبْقِي مَوْرِداً فائِضاً وَمَرْعَى ً خَصِيبا", "sadr": " كَالغَمَامِ الرُّكامِ يَمْضِي وَيُبْقِي", "ajez": " مَوْرِداً فائِضاً وَمَرْعَى ً خَصِيبا"}, {"bayt": " فُرْقَة ٌ يا أَبا الْعَلاَءِ أَصارَتْ حسناتِ الزمانِ عندي ذنوبا", "sadr": " فُرْقَة ٌ يا أَبا الْعَلاَءِ أَصارَتْ", "ajez": " حسناتِ الزمانِ عندي ذنوبا"}, {"bayt": " كمْ سبقتَ الجارينَ في حلبة ِ المجـ ـدِ وَكَلُّوا وَما شَكَوْتَ لُغُوبا", "sadr": " كمْ سبقتَ الجارينَ في حلبة ِ المجـ", "ajez": " ـدِ وَكَلُّوا وَما شَكَوْتَ لُغُوبا"}, {"bayt": " لا كما يسبقُ المجاري المجارى بَلْ كَما يَسْبِقُ الشَّبابُ الْمَشِيبا", "sadr": " لا كما يسبقُ المجاري المجارى", "ajez": " بَلْ كَما يَسْبِقُ الشَّبابُ الْمَشِيبا"}, {"bayt": " لمْ يزلْ جانبي منيعاً مهيباً مذْ رأتني بكَ الخطوبُ مهيبا", "sadr": " لمْ يزلْ جانبي منيعاً مهيباً", "ajez": " مذْ رأتني بكَ الخطوبُ مهيبا"}, {"bayt": " وَلِهَذَا أَصْبَحْتُ مِنْ أَلَمِ الْفُرْ قة ِ أوفى مفارقيكَ نصيبا", "sadr": " وَلِهَذَا أَصْبَحْتُ مِنْ أَلَمِ الْفُرْ", "ajez": " قة ِ أوفى مفارقيكَ نصيبا"}, {"bayt": " وَلوْ أني ملكتُ نفسي وَرأيي لَوَصَلتُ الإِسْآدَ وَالتَّأْوِيبا", "sadr": " وَلوْ أني ملكتُ نفسي وَرأيي", "ajez": " لَوَصَلتُ الإِسْآدَ وَالتَّأْوِيبا"}, {"bayt": " فكفاني مؤونة َ الشوقِ عزمٌ لاَ يملُّ التقويضَ وَ التطنيبا", "sadr": " فكفاني مؤونة َ الشوقِ عزمٌ", "ajez": " لاَ يملُّ التقويضَ وَ التطنيبا"}, {"bayt": " غَيْرَ أَنِّي الْقَلْبَ عِلْماً أَنَّهُ لاَ يَؤُوبُ حَتَّى تَؤُوبا", "sadr": " غَيْرَ أَنِّي الْقَلْبَ عِلْماً", "ajez": " أَنَّهُ لاَ يَؤُوبُ حَتَّى تَؤُوبا"}], "era": "العصر العباسي", "title": "كُنْ بَعِيداً إِنْ شِئْتَ أَوْ كُنْ قَرِيبا"}